{
  "cve_id": "CVE-2024-10026",
  "description": "A **weak hashing algorithm and small sizes of seeds/secrets** in Googles gVisor allowed for a remote attacker to calculate a local IP address and a per-boot identifier that could aid in tracking of a device in certain circumstances.",
  "key_phrases": {
    "rootcause": "weak hashing algorithm and small sizes of seeds/secrets",
    "weakness": "",
    "impact": "calculate a local IP address and a per-boot identifier",
    "vector": "",
    "attacker": "remote attacker",
    "product": "Googles gVisor",
    "version": "",
    "component": ""
  },
  "reference_content": "Here's an analysis of the provided content, focusing on potential vulnerabilities and security improvements related to CVE-2024-10026, which is a placeholder.\n\n**Based on the provided content, the most relevant findings relate to improvements in cryptographic security within the gVisor project.**\n\n**Content from github.com_44efcceb_20250624_164317.html (stripped)**\n\n*   **Relevance:** This commit introduces a cryptographically secure RNG (Random Number Generator) to replace the default PRNG (Pseudo-Random Number Generator) where appropriate. This aligns with the general security principle of using strong randomness.\n*   **Root cause of vulnerability:** The original code used a PRNG in places where a cryptographically secure RNG was needed. This could lead to predictable values and potential vulnerabilities in protocols that rely on randomness.\n*   **Weaknesses/vulnerabilities present:** Using a PRNG instead of a cryptographically secure RNG can lead to:\n    *   **Predictable values:** An attacker might be able to predict the output of the PRNG, especially if the seed or internal state is known or can be influenced.\n    *   **Weak security in protocols:** This can be exploited in network protocols like TCP/IP, which use random numbers for sequence number generation, nonce generation, and other security-sensitive operations.\n*   **Impact of exploitation:**\n    *   **Sequence number prediction:** An attacker could predict TCP sequence numbers, allowing them to inject packets, hijack connections, or disrupt communication.\n    *   **Weakened cryptographic operations:** If the PRNG is used in other cryptographic contexts (e.g., key generation, nonce creation), the security of those operations could be compromised.\n*   **Attack vectors:** Exploitation could involve analyzing network traffic to gather information about the PRNG's output or influencing the PRNG's internal state.\n*   **Required attacker capabilities/position:** An attacker would need to be able to observe network traffic, possibly inject packets, and understand the gVisor's internal workings to exploit the weaknesses.\n*   **Mitigation or fix:**\n    *   The commit **addresses the vulnerability by introducing a cryptographically secure RNG (RNG) and using it in place of the insecure PRNG**. Specifically, it changes the code to use the new RNG in network protocols, such as ARP and IPv6.\n    *   The commit renames the default PRNG to `InsecureRNG` to make it more obvious to future contributors that some RNGs are inappropriate in certain instances.\n    *   The commit also includes changes to tests that were injecting fake RNGs and had to be relaxed.\n\n**Content from github.com_b5cf8d40_20250624_164319.html (stripped)**\n\n*   **Relevance:** This commit focuses on enhancing the security of Initial Sequence Number (ISN) generation in the TCP implementation.\n*   **Root cause of vulnerability:** The original code used a 32-bit seed for the SHA-1 hash function, making it short for hashing.\n*   **Weaknesses/vulnerabilities present:** Use of a short secret for the SHA hash algorithm can lead to a security concern.\n*   **Impact of exploitation:** An attacker could have predicted TCP sequence numbers.\n*   **Mitigation or fix:** The commit **addresses the vulnerability by using 16-byte secret for SHA256 hash function**. This increases the security of the ISN generation process.\n\n**Content from github.com_e18fa7a5_20250624_164321.html (stripped)**\n\n*   **Relevance:** This commit replaces the use of the Jenkins hash function with SHA256 for generating ISNs and timestamp offsets in TCP.\n*   **Root cause of vulnerability:** The original code used the Jenkins hash function, which is not cryptographically secure, to generate Initial Sequence Numbers (ISNs) and timestamp offsets in TCP. This could lead to predictable ISNs, which could be exploited.\n*   **Weaknesses/vulnerabilities present:**\n    *   **Predictable ISNs:** An attacker could potentially predict the ISNs, enabling them to inject malicious packets, hijack connections, or disrupt network communication.\n    *   **Weak timestamp offsets:** Similarly, the timestamp offsets could be predictable, potentially leading to attacks on TCP timestamp-based security mechanisms.\n*   **Impact of exploitation:** The impact would be the same as the impact described for the previous commit.\n*   **Attack vectors:**\n    *   **Traffic analysis:** An attacker could analyze network traffic to gather information about the Jenkins hash function's output and, from that, predict ISNs or timestamp offsets.\n*   **Required attacker capabilities/position:**\n    *   The attacker would need to be able to capture network traffic, understand the gVisor TCP implementation, and have some knowledge of the Jenkins hash function.\n*   **Mitigation or fix:**\n    *   The commit **replaces the Jenkins hash function with the cryptographically secure SHA256 algorithm**. This makes the ISNs and timestamp offsets much more difficult to predict, improving the security of the TCP implementation.\n    *   The commit changes the code to use the SHA256 algorithm for generating both ISNs and timestamp offsets.\n\n**Summary**\n\nThese commits address the security of gVisor by strengthening the generation of random numbers and cryptographic keys. The identified vulnerabilities are related to the predictability of values generated by weaker hash functions and PRNGs. The fix involves replacing these with more secure, cryptographic functions.",
  "similar_info": {
    "cwe_distribution": {},
    "cwe_consensus": "",
    "similarity_stats": {
      "thresholds": [],
      "total_samples_by_threshold": {},
      "top_cwes_by_threshold": {}
    }
  },
  "similarity_summary": {
    "consensus_cwe": "",
    "top_cwes": [],
    "confidence_levels": {},
    "total_samples": 0
  },
  "analysis": "# Summary\n| CWE ID | CWE Name | Confidence | CWE Abstraction Level | CWE Vulnerability Mapping Label | CWE-Vulnerability Mapping Notes |\n|---|---|---|---|---|---|\n| CWE-328 | Use of Weak Hash | 0.9 | Base | Primary | Allowed |\n| CWE-335 | Incorrect Usage of Seeds in Pseudo-Random Number Generator (PRNG) | 0.8 | Base | Secondary | Allowed |\n\n## Evidence and Confidence\n\n*   **Confidence Score:** 0.85\n*   **Evidence Strength:** HIGH\n\n## Relationship Analysis\nThe primary CWE, CWE-328, is a base-level weakness that directly reflects the use of a weak hashing algorithm. It is a child of CWE-326 and CWE-327. CWE-335, a secondary CWE, is also a base-level weakness indicating incorrect usage of seeds in PRNG. It is a child of CWE-330. The relationship analysis suggests that the root cause involves multiple contributing factors related to randomness and cryptography.\n\n```mermaid\ngraph TD\n    cwe328[\"CWE-328: Use of Weak Hash\"]\n    cwe326[\"CWE-326: Inadequate Encryption Strength\"]\n    cwe327[\"CWE-327: Use of a Broken or Risky Cryptographic Algorithm\"]\n    cwe335[\"CWE-335: Incorrect Usage of Seeds in Pseudo-Random Number Generator (PRNG)\"]\n    cwe330[\"CWE-330: Use of Insufficiently Random Values\"]\n    \n    cwe328 -->|CHILDOF| cwe326\n    cwe328 -->|CHILDOF| cwe327\n    cwe335 -->|CHILDOF| cwe330\n    \n    classDef primary fill:#f96,stroke:#333,stroke-width:2px\n    classDef secondary fill:#69f,stroke:#333\n    classDef tertiary fill:#9e9,stroke:#333\n    class cwe328 primary\n    class cwe335 secondary\n    class cwe326,cwe327,cwe330 tertiary\n```\n\n## Vulnerability Chain\nThe vulnerability chain starts with the **use of a weak hashing algorithm and small sizes of seeds/secrets**. This leads to the ability to calculate a local IP address and a per-boot identifier, which could aid in tracking a device. The root causes are CWE-328 and CWE-335 and the impact is device tracking.\n\n## Summary of Analysis\nThe initial analysis identified the **weak hashing algorithm and small sizes of seeds/secrets** as the root cause. The vulnerability description and CVE reference links provide sufficient evidence to support this assessment.\n\nThe selection of CWE-328 and CWE-335 is based on the following evidence:\n\n*   The vulnerability description explicitly mentions a \"**weak hashing algorithm and small sizes of seeds/secrets**\".\n*   The CVE reference links confirm the use of weaker algorithms like Jenkins hash and SHA-1 with short seeds, and also highlights the replacement of PRNG with cryptographically secure RNGs.\n\nCWE-328 (Use of Weak Hash) is a base-level CWE that accurately describes the use of a weak hashing algorithm, as indicated in the vulnerability description and CVE reference links. CWE-335 (Incorrect Usage of Seeds in Pseudo-Random Number Generator (PRNG)) is also a base-level CWE that accurately describes the issue of using small sizes of seeds/secrets.\n\nOther CWEs were considered but not selected:\n\n*   CWE-656 (Reliance on Security Through Obscurity): While the use of a weak hash might be considered a form of security through obscurity, the primary issue is the weakness of the algorithm itself, not the reliance on its obscurity.\n*   CWE-330 (Use of Insufficiently Random Values): While related to the use of small seeds, CWE-335 is more specific in addressing the incorrect management of seeds in PRNGs.\n*   CWE-916 (Use of Password Hash With Insufficient Computational Effort): This CWE is specific to password hashing, which is not the primary focus of the vulnerability.\n\nThe selected CWEs are at the optimal level of specificity because they directly address the root causes identified in the vulnerability description and CVE reference links.\n\nRelevant CWE Information:\n\n# Enhanced Context (25 CWEs)\nThe following CWEs were identified as potentially relevant to this vulnerability:\n\n## CWE-1240: Use of a Cryptographic Primitive with a Risky Implementation\n**Abstraction Level**: Base\n**Similarity Score**: 0.79\n**Source**: dense\n\n**Description**:\nTo fulfill the need for a cryptographic primitive, the product implements a cryptographic algorithm using a non-standard, unproven, or disallowed/non-compliant cryptographic implementation.\n\n**Mapping Guidance**:\n- Usage: Allowed\n- Rationale: This CWE entry is at the Base level of abstraction, which is a preferred level of abstraction for mapping to the root causes of vulnerabilities.\n\n## CWE-335: Incorrect Usage of Seeds in Pseudo-Random Number Generator (PRNG)\n**Abstraction Level**: Base\n**Similarity Score**: 0.79\n**Source**: dense\n\n**Description**:\nThe product uses a Pseudo-Random Number Generator (PRNG) but does not correctly manage seeds.\n\n**Mapping Guidance**:\n- Usage: Allowed\n- Rationale: This CWE entry is at the Base level of abstraction, which is a preferred level of abstraction for mapping to the root causes of vulnerabilities.\n\n## CWE-330: Use of Insufficiently Random Values\n**Abstraction Level**: Class\n**Similarity Score**: 0.79\n**Source**: dense\n\n**Description**:\nThe product uses insufficiently random numbers or values in a security context that depends on unpredictable numbers.\n\n**Mapping Guidance**:\n- Usage: Discouraged\n- Rationale: This CWE entry is a level-1 Class (i.e., a child of a Pillar). It might have lower-level children that would be more appropriate\n\n## CWE-328: Use of Weak Hash\n**Abstraction Level**: Base\n**Similarity Score**: 0.78\n**Source**: dense\n\n**Description**:\nThe product uses an algorithm that produces a digest (output value) that does not meet security expectations for a hash function that allows an adversary to reasonably determine the original input (preimage attack), find another input that can produce the same hash (2nd preimage attack), or find multiple inputs that evaluate to the same hash (birthday attack).\n\n**Mapping Guidance**:\n- Usage: Allowed\n- Rationale: This CWE entry is at the Base level of abstraction, which is a preferred level of abstraction for mapping to the root causes of vulnerabilities.\n\n## CWE-1391: Use of Weak Credentials\n**Abstraction Level**: Class\n**Similarity Score**: 0.78\n**Source**: dense\n\n**Description**:\nThe product uses weak credentials (such as a default key or hard-coded password) that can be calculated, derived, reused, or guessed by an attacker.\n\n**Mapping Guidance**:\n- Usage: Allowed-with-Review\n- Rationale: This CWE entry is a Class and might have Base-level children that would be more appropriate\n\n## CWE-916: Use of Password Hash With Insufficient Computational Effort\n**Abstraction Level**: Base\n**Similarity Score**: 0.78\n**Source**: dense\n\n**Description**:\nThe product generates a hash for a password, but it uses a scheme that does not provide a sufficient level of computational effort that would make password cracking attacks infeasible or expensive.\n\n**Mapping Guidance**:\n- Usage: Allowed\n- Rationale: This CWE entry is at the Base level of abstraction, which is a preferred level of abstraction for mapping to the root causes of vulnerabilities.\n\n## CWE-331: Insufficient Entropy\n**Abstraction Level**: Base\n**Similarity Score**: 0.76\n**Source**: dense\n\n**Description**:\nThe product uses an algorithm or scheme that produces insufficient entropy, leaving patterns or clusters of values that are more likely to occur than others.\n\n**Mapping Guidance**:\n- Usage: Allowed\n- Rationale: This CWE entry is at the Base level of abstraction, which is a preferred level of abstraction for mapping to the root causes of vulnerabilities.\n\n## CWE-798: Use of Hard-coded Credentials\n**Abstraction Level**: Base\n**Similarity Score**: 0.76\n**Source**: dense\n\n**Description**:\nThe product contains hard-coded credentials, such as a password or cryptographic key.\n\n**Mapping Guidance**:\n- Usage: Allowed\n- Rationale: This CWE entry is at the Base level of abstraction, which is a preferred level of abstraction for mapping to the root causes of vulnerabilities.\n\n## CWE-321: Use of Hard-coded Cryptographic Key\n**Abstraction Level**: Variant\n**Similarity Score**: 0.75\n**Source**: dense\n\n**Description**:\nThe use of a hard-coded cryptographic key significantly increases the possibility that encrypted data may be recovered.\n\n**Mapping Guidance**:\n- Usage: Allowed\n- Rationale: This CWE entry is at the Variant level of abstraction, which is a preferred level of abstraction for mapping to the root causes of vulnerabilities.\n\n## CWE-345: Insufficient Verification of Data Authenticity\n**Abstraction Level**: Class\n**Similarity Score**: 0.75\n**Source**: dense\n\n**Description**:\nThe product does not sufficiently verify the origin or authenticity of data, in a way that causes it to accept invalid data.\n\n**Mapping Guidance**:\n- Usage: Discouraged\n- Rationale: This CWE entry is a level-1 Class (i.e., a child of a Pillar). It might have lower-level children that would be more appropriate\n\n## CWE-916: Use of Password Hash With Insufficient Computational Effort\n**Abstraction Level**: Base\n**Similarity Score**: 9130.77\n**Source**: sparse\n\n**Description**:\nThe product generates a hash for a password, but it uses a scheme that does not provide a sufficient level of computational effort that would make password cracking attacks infeasible or expensive.\n\n**Mapping Guidance**:\n- Usage: Allowed\n- Rationale: This CWE entry is at the Base level of abstraction, which is a preferred level of abstraction for mapping to the root causes of vulnerabilities.\n\n## CWE-335: Incorrect Usage of Seeds in Pseudo-Random Number Generator (PRNG)\n**Abstraction Level**: Base\n**Similarity Score**: 8646.21\n**Source**: sparse\n\n**Description**:\nThe product uses a Pseudo-Random Number Generator (PRNG) but does not correctly manage seeds.\n\n**Mapping Guidance**:\n- Usage: Allowed\n- Rationale: This CWE entry is at the Base level of abstraction, which is a preferred level of abstraction for mapping to the root causes of vulnerabilities.\n\n## CWE-328: Use of Weak Hash\n**Abstraction Level**: Base\n**Similarity Score**: 8558.50\n**Source**: sparse\n\n**Description**:\nThe product uses an algorithm that produces a digest (output value) that does not meet security expectations for a hash function that allows an adversary to reasonably determine the original input (preimage attack), find another input that can produce the same hash (2nd preimage attack), or find multiple inputs that evaluate to the same hash (birthday attack).\n\n**Mapping Guidance**:\n- Usage: Allowed\n- Rationale: This CWE entry is at the Base level of abstraction, which is a preferred level of abstraction for mapping to the root causes of vulnerabilities.\n\n## CWE-330: Use of Insufficiently Random Values\n**Abstraction Level**: Class\n**Similarity Score**: 8466.01\n**Source**: sparse\n\n**Description**:\nThe product uses insufficiently random numbers or values in a security context that depends on unpredictable numbers.\n\n**Mapping Guidance**:\n- Usage: Discouraged\n- Rationale: This CWE entry is a level-1 Class (i.e., a child of a Pillar). It might have lower-level children that would be more appropriate\n\n## CWE-338: Use of Cryptographically Weak Pseudo-Random Number Generator (PRNG)\n**Abstraction Level**: Base\n**Similarity Score**: 8396.29\n**Source**: sparse\n\n**Description**:\nThe product uses a Pseudo-Random Number Generator (PRNG) in a security context, but the PRNG's algorithm is not cryptographically strong.\n\n**Mapping Guidance**:\n- Usage: Allowed\n- Rationale: This CWE entry is at the Base level of abstraction, which is a preferred level of abstraction for mapping to the root causes of vulnerabilities.\n\n## CWE-259: Use of Hard-coded Password\n**Abstraction Level**: variant\n**Similarity Score**: 4.53\n**Source**: graph\n\n**Description**:\nCWE-259: Use of Hard-coded Password\n\n**Mapping Guidance**:\n- Usage: Allowed\n- Rationale: This CWE entry is at the Variant level of abstraction, which is a preferred level of abstraction for mapping to the root causes of vulnerabilities.\n\n**Relationships**:\n- CANFOLLOW -> CWE-656\n- PEEROF -> CWE-257\n- PEEROF -> CWE-321\n- CHILDOF -> CWE-798\n- CHILDOF -> CWE-798\n\n## CWE-472: External Control of Assumed-Immutable Web Parameter\n**Abstraction Level**: base\n**Similarity Score**: 4.33\n**Source**: graph\n\n**Description**:\nCWE-472: External Control of Assumed-Immutable Web Parameter\n\n**Mapping Guidance**:\n- Usage: Allowed\n- Rationale: This CWE entry is at the Base level of abstraction, which is a preferred level of abstraction for mapping to the root causes of vulnerabilities.\n\n**Relationships**:\n- CANFOLLOW -> CWE-656\n- REQUIREDBY -> CWE-384\n- CHILDOF -> CWE-471\n- CHILDOF -> CWE-642\n- CANPRECEDE -> CWE-472\n\n## CWE-804: Guessable CAPTCHA\n**Abstraction Level**: base\n**Similarity Score**: 4.33\n**Source**: graph\n\n**Description**:\nCWE-804: Guessable CAPTCHA\n\n**Mapping Guidance**:\n- Usage: Allowed\n- Rationale: This CWE entry is at the Base level of abstraction, which is a preferred level of abstraction for mapping to the root causes of vulnerabilities.\n\n**Relationships**:\n- CANFOLLOW -> CWE-330\n- CHILDOF -> CWE-1390\n- CHILDOF -> CWE-863\n- PARENTOF -> CWE-804\n- CANPRECEDE -> CWE-804\n\n## CWE-603: Use of Client-Side Authentication\n**Abstraction Level**: base\n**Similarity Score**: 3.64\n**Source**: graph\n\n**Description**:\nCWE-603: Use of Client-Side Authentication\n\n**Mapping Guidance**:\n- Usage: Allowed\n- Rationale: This CWE entry is at the Base level of abstraction, which is a preferred level of abstraction for mapping to the root causes of vulnerabilities.\n\n**Relationships**:\n- PEEROF -> CWE-656\n- PEEROF -> CWE-300\n- CHILDOF -> CWE-602\n- CHILDOF -> CWE-1390\n- PARENTOF -> CWE-603\n\n## CWE-321: Use of Hard-coded Cryptographic Key\n**Abstraction Level**: Variant\n**Similarity Score**: 3.02\n**Source**: graph\n\n**Description**:\nThe use of a hard-coded cryptographic key significantly increases the possibility that encrypted data may be recovered.\n\n**Mapping Guidance**:\n- Usage: Allowed\n- Rationale: This CWE entry is at the Variant level of abstraction, which is a preferred level of abstraction for mapping to the root causes of vulnerabilities.\n\n**Relationships**:\n- CANFOLLOW -> CWE-656\n- CHILDOF -> CWE-798\n- CHILDOF -> CWE-798\n- CHILDOF -> CWE-798\n- PARENTOF -> CWE-321\n\n## CWE-1272: Sensitive Information Uncleared Before Debug/Power State Transition\n**Abstraction Level**: base\n**Similarity Score**: 2.21\n**Source**: graph\n\n**Description**:\nCWE-1272: Sensitive Information Uncleared Before Debug/Power State Transition\n\n**Mapping Guidance**:\n- Usage: Allowed\n- Rationale: This CWE entry is at the Base level of abstraction, which is a preferred level of abstraction for mapping to the root causes of vulnerabilities.\n\n**Relationships**:\n- CANPRECEDE -> CWE-200\n- CHILDOF -> CWE-226\n- PARENTOF -> CWE-1272\n- CANFOLLOW -> CWE-1272\n\n## CWE-1291: Public Key Re-Use for Signing both Debug and Production Code\n**Abstraction Level**: base\n**Similarity Score**: 2.18\n**Source**: graph\n\n**Description**:\nCWE-1291: Public Key Re-Use for Signing both Debug and Production Code\n\n**Mapping Guidance**:\n- Usage: Allowed\n- Rationale: This CWE entry is at the Base level of abstraction, which is a preferred level of abstraction for mapping to the root causes of vulnerabilities.\n\n**Relationships**:\n- PEEROF -> CWE-321\n- CHILDOF -> CWE-693\n- PARENTOF -> CWE-1291\n\n## CWE-760: Use of a One-Way Hash with a Predictable Salt\n**Abstraction Level**: variant\n**Similarity Score**: 2.16\n**Source**: graph\n\n**Description**:\nCWE-760: Use of a One-Way Hash with a Predictable Salt\n\n**Mapping Guidance**:\n- Usage: Allowed\n- Rationale: This CWE entry is at the Variant level of abstraction, which is a preferred level of abstraction for mapping to the root causes of vulnerabilities.\n\n**Relationships**:\n- CHILDOF -> CWE-916\n- PARENTOF -> CWE-760\n\n## CWE-337: Predictable Seed in Pseudo-Random Number Generator (PRNG)\n**Abstraction Level**: variant\n**Similarity Score**: 2.16\n**Source**: graph\n\n**Description**:\nCWE-337: Predictable Seed in Pseudo-Random Number Generator (PRNG)\n\n**Mapping Guidance**:\n- Usage: Allowed\n- Rationale: This CWE entry is at the Variant level of abstraction, which is a preferred level of abstraction for mapping to the root causes of vulnerabilities.\n\n**Relationships**:\n- CHILDOF -> CWE-335\n- PARENTOF -> CWE",
  "analysis_with_relationships": "# Summary\n| CWE ID | CWE Name | Confidence | CWE Abstraction Level | CWE Vulnerability Mapping Label | CWE-Vulnerability Mapping Notes |\n|---|---|---|---|---|---|\n| CWE-328 | Use of Weak Hash | 0.9 | Base | Primary | Allowed |\n| CWE-335 | Incorrect Usage of Seeds in Pseudo-Random Number Generator (PRNG) | 0.8 | Base | Secondary | Allowed |\n\n## Evidence and Confidence\n\n*   **Confidence Score:** 0.85\n*   **Evidence Strength:** HIGH\n\n## Relationship Analysis\nThe primary CWE, CWE-328, is a base-level weakness that directly reflects the use of a weak hashing algorithm. It is a child of CWE-326 and CWE-327. CWE-335, a secondary CWE, is also a base-level weakness indicating incorrect usage of seeds in PRNG. It is a child of CWE-330. The relationship analysis suggests that the root cause involves multiple contributing factors related to randomness and cryptography.\n\n```mermaid\ngraph TD\n    cwe328[\"CWE-328: Use of Weak Hash\"]\n    cwe326[\"CWE-326: Inadequate Encryption Strength\"]\n    cwe327[\"CWE-327: Use of a Broken or Risky Cryptographic Algorithm\"]\n    cwe335[\"CWE-335: Incorrect Usage of Seeds in Pseudo-Random Number Generator (PRNG)\"]\n    cwe330[\"CWE-330: Use of Insufficiently Random Values\"]\n    \n    cwe328 -->|CHILDOF| cwe326\n    cwe328 -->|CHILDOF| cwe327\n    cwe335 -->|CHILDOF| cwe330\n    \n    classDef primary fill:#f96,stroke:#333,stroke-width:2px\n    classDef secondary fill:#69f,stroke:#333\n    classDef tertiary fill:#9e9,stroke:#333\n    class cwe328 primary\n    class cwe335 secondary\n    class cwe326,cwe327,cwe330 tertiary\n```\n\n## Vulnerability Chain\nThe vulnerability chain starts with the **use of a weak hashing algorithm and small sizes of seeds/secrets**. This leads to the ability to calculate a local IP address and a per-boot identifier, which could aid in tracking a device. The root causes are CWE-328 and CWE-335 and the impact is device tracking.\n\n## Summary of Analysis\nThe initial analysis identified the **weak hashing algorithm and small sizes of seeds/secrets** as the root cause. The vulnerability description and CVE reference links provide sufficient evidence to support this assessment.\n\nThe selection of CWE-328 and CWE-335 is based on the following evidence:\n\n*   The vulnerability description explicitly mentions a \"**weak hashing algorithm and small sizes of seeds/secrets**\".\n*   The CVE reference links confirm the use of weaker algorithms like Jenkins hash and SHA-1 with short seeds, and also highlights the replacement of PRNG with cryptographically secure RNGs.\n\nCWE-328 (Use of Weak Hash) is a base-level CWE that accurately describes the use of a weak hashing algorithm, as indicated in the vulnerability description and CVE reference links. CWE-335 (Incorrect Usage of Seeds in Pseudo-Random Number Generator (PRNG)) is also a base-level CWE that accurately describes the issue of using small sizes of seeds/secrets.\n\nOther CWEs were considered but not selected:\n\n*   CWE-656 (Reliance on Security Through Obscurity): While the use of a weak hash might be considered a form of security through obscurity, the primary issue is the weakness of the algorithm itself, not the reliance on its obscurity.\n*   CWE-330 (Use of Insufficiently Random Values): While related to the use of small seeds, CWE-335 is more specific in addressing the incorrect management of seeds in PRNGs.\n*   CWE-916 (Use of Password Hash With Insufficient Computational Effort): This CWE is specific to password hashing, which is not the primary focus of the vulnerability.\n\nThe selected CWEs are at the optimal level of specificity because they directly address the root causes identified in the vulnerability description and CVE reference links.\n\nRelevant CWE Information:\n\n# Enhanced Context (25 CWEs)\nThe following CWEs were identified as potentially relevant to this vulnerability:\n\n## CWE-1240: Use of a Cryptographic Primitive with a Risky Implementation\n**Abstraction Level**: Base\n**Similarity Score**: 0.79\n**Source**: dense\n\n**Description**:\nTo fulfill the need for a cryptographic primitive, the product implements a cryptographic algorithm using a non-standard, unproven, or disallowed/non-compliant cryptographic implementation.\n\n**Mapping Guidance**:\n- Usage: Allowed\n- Rationale: This CWE entry is at the Base level of abstraction, which is a preferred level of abstraction for mapping to the root causes of vulnerabilities.\n\n## CWE-335: Incorrect Usage of Seeds in Pseudo-Random Number Generator (PRNG)\n**Abstraction Level**: Base\n**Similarity Score**: 0.79\n**Source**: dense\n\n**Description**:\nThe product uses a Pseudo-Random Number Generator (PRNG) but does not correctly manage seeds.\n\n**Mapping Guidance**:\n- Usage: Allowed\n- Rationale: This CWE entry is at the Base level of abstraction, which is a preferred level of abstraction for mapping to the root causes of vulnerabilities.\n\n## CWE-330: Use of Insufficiently Random Values\n**Abstraction Level**: Class\n**Similarity Score**: 0.79\n**Source**: dense\n\n**Description**:\nThe product uses insufficiently random numbers or values in a security context that depends on unpredictable numbers.\n\n**Mapping Guidance**:\n- Usage: Discouraged\n- Rationale: This CWE entry is a level-1 Class (i.e., a child of a Pillar). It might have lower-level children that would be more appropriate\n\n## CWE-328: Use of Weak Hash\n**Abstraction Level**: Base\n**Similarity Score**: 0.78\n**Source**: dense\n\n**Description**:\nThe product uses an algorithm that produces a digest (output value) that does not meet security expectations for a hash function that allows an adversary to reasonably determine the original input (preimage attack), find another input that can produce the same hash (2nd preimage attack), or find multiple inputs that evaluate to the same hash (birthday attack).\n\n**Mapping Guidance**:\n- Usage: Allowed\n- Rationale: This CWE entry is at the Base level of abstraction, which is a preferred level of abstraction for mapping to the root causes of vulnerabilities.\n\n## CWE-1391: Use of Weak Credentials\n**Abstraction Level**: Class\n**Similarity Score**: 0.78\n**Source**: dense\n\n**Description**:\nThe product uses weak credentials (such as a default key or hard-coded password) that can be calculated, derived, reused, or guessed by an attacker.\n\n**Mapping Guidance**:\n- Usage: Allowed-with-Review\n- Rationale: This CWE entry is a Class and might have Base-level children that would be more appropriate\n\n## CWE-916: Use of Password Hash With Insufficient Computational Effort\n**Abstraction Level**: Base\n**Similarity Score**: 0.78\n**Source**: dense\n\n**Description**:\nThe product generates a hash for a password, but it uses a scheme that does not provide a sufficient level of computational effort that would make password cracking attacks infeasible or expensive.\n\n**Mapping Guidance**:\n- Usage: Allowed\n- Rationale: This CWE entry is at the Base level of abstraction, which is a preferred level of abstraction for mapping to the root causes of vulnerabilities.\n\n## CWE-331: Insufficient Entropy\n**Abstraction Level**: Base\n**Similarity Score**: 0.76\n**Source**: dense\n\n**Description**:\nThe product uses an algorithm or scheme that produces insufficient entropy, leaving patterns or clusters of values that are more likely to occur than others.\n\n**Mapping Guidance**:\n- Usage: Allowed\n- Rationale: This CWE entry is at the Base level of abstraction, which is a preferred level of abstraction for mapping to the root causes of vulnerabilities.\n\n## CWE-798: Use of Hard-coded Credentials\n**Abstraction Level**: Base\n**Similarity Score**: 0.76\n**Source**: dense\n\n**Description**:\nThe product contains hard-coded credentials, such as a password or cryptographic key.\n\n**Mapping Guidance**:\n- Usage: Allowed\n- Rationale: This CWE entry is at the Base level of abstraction, which is a preferred level of abstraction for mapping to the root causes of vulnerabilities.\n\n## CWE-321: Use of Hard-coded Cryptographic Key\n**Abstraction Level**: Variant\n**Similarity Score**: 0.75\n**Source**: dense\n\n**Description**:\nThe use of a hard-coded cryptographic key significantly increases the possibility that encrypted data may be recovered.\n\n**Mapping Guidance**:\n- Usage: Allowed\n- Rationale: This CWE entry is at the Variant level of abstraction, which is a preferred level of abstraction for mapping to the root causes of vulnerabilities.\n\n## CWE-345: Insufficient Verification of Data Authenticity\n**Abstraction Level**: Class\n**Similarity Score**: 0.75\n**Source**: dense\n\n**Description**:\nThe product does not sufficiently verify the origin or authenticity of data, in a way that causes it to accept invalid data.\n\n**Mapping Guidance**:\n- Usage: Discouraged\n- Rationale: This CWE entry is a level-1 Class (i.e., a child of a Pillar). It might have lower-level children that would be more appropriate\n\n## CWE-916: Use of Password Hash With Insufficient Computational Effort\n**Abstraction Level**: Base\n**Similarity Score**: 9130.77\n**Source**: sparse\n\n**Description**:\nThe product generates a hash for a password, but it uses a scheme that does not provide a sufficient level of computational effort that would make password cracking attacks infeasible or expensive.\n\n**Mapping Guidance**:\n- Usage: Allowed\n- Rationale: This CWE entry is at the Base level of abstraction, which is a preferred level of abstraction for mapping to the root causes of vulnerabilities.\n\n## CWE-335: Incorrect Usage of Seeds in Pseudo-Random Number Generator (PRNG)\n**Abstraction Level**: Base\n**Similarity Score**: 8646.21\n**Source**: sparse\n\n**Description**:\nThe product uses a Pseudo-Random Number Generator (PRNG) but does not correctly manage seeds.\n\n**Mapping Guidance**:\n- Usage: Allowed\n- Rationale: This CWE entry is at the Base level of abstraction, which is a preferred level of abstraction for mapping to the root causes of vulnerabilities.\n\n## CWE-328: Use of Weak Hash\n**Abstraction Level**: Base\n**Similarity Score**: 8558.50\n**Source**: sparse\n\n**Description**:\nThe product uses an algorithm that produces a digest (output value) that does not meet security expectations for a hash function that allows an adversary to reasonably determine the original input (preimage attack), find another input that can produce the same hash (2nd preimage attack), or find multiple inputs that evaluate to the same hash (birthday attack).\n\n**Mapping Guidance**:\n- Usage: Allowed\n- Rationale: This CWE entry is at the Base level of abstraction, which is a preferred level of abstraction for mapping to the root causes of vulnerabilities.\n\n## CWE-330: Use of Insufficiently Random Values\n**Abstraction Level**: Class\n**Similarity Score**: 8466.01\n**Source**: sparse\n\n**Description**:\nThe product uses insufficiently random numbers or values in a security context that depends on unpredictable numbers.\n\n**Mapping Guidance**:\n- Usage: Discouraged\n- Rationale: This CWE entry is a level-1 Class (i.e., a child of a Pillar). It might have lower-level children that would be more appropriate\n\n## CWE-338: Use of Cryptographically Weak Pseudo-Random Number Generator (PRNG)\n**Abstraction Level**: Base\n**Similarity Score**: 8396.29\n**Source**: sparse\n\n**Description**:\nThe product uses a Pseudo-Random Number Generator (PRNG) in a security context, but the PRNG's algorithm is not cryptographically strong.\n\n**Mapping Guidance**:\n- Usage: Allowed\n- Rationale: This CWE entry is at the Base level of abstraction, which is a preferred level of abstraction for mapping to the root causes of vulnerabilities.\n\n## CWE-259: Use of Hard-coded Password\n**Abstraction Level**: variant\n**Similarity Score**: 4.53\n**Source**: graph\n\n**Description**:\nCWE-259: Use of Hard-coded Password\n\n**Mapping Guidance**:\n- Usage: Allowed\n- Rationale: This CWE entry is at the Variant level of abstraction, which is a preferred level of abstraction for mapping to the root causes of vulnerabilities.\n\n**Relationships**:\n- CANFOLLOW -> CWE-656\n- PEEROF -> CWE-257\n- PEEROF -> CWE-321\n- CHILDOF -> CWE-798\n- CHILDOF -> CWE-798\n\n## CWE-472: External Control of Assumed-Immutable Web Parameter\n**Abstraction Level**: base\n**Similarity Score**: 4.33\n**Source**: graph\n\n**Description**:\nCWE-472: External Control of Assumed-Immutable Web Parameter\n\n**Mapping Guidance**:\n- Usage: Allowed\n- Rationale: This CWE entry is at the Base level of abstraction, which is a preferred level of abstraction for mapping to the root causes of vulnerabilities.\n\n**Relationships**:\n- CANFOLLOW -> CWE-656\n- REQUIREDBY -> CWE-384\n- CHILDOF -> CWE-471\n- CHILDOF -> CWE-642\n- CANPRECEDE -> CWE-472\n\n## CWE-804: Guessable CAPTCHA\n**Abstraction Level**: base\n**Similarity Score**: 4.33\n**Source**: graph\n\n**Description**:\nCWE-804: Guessable CAPTCHA\n\n**Mapping Guidance**:\n- Usage: Allowed\n- Rationale: This CWE entry is at the Base level of abstraction, which is a preferred level of abstraction for mapping to the root causes of vulnerabilities.\n\n**Relationships**:\n- CANFOLLOW -> CWE-330\n- CHILDOF -> CWE-1390\n- CHILDOF -> CWE-863\n- PARENTOF -> CWE-804\n- CANPRECEDE -> CWE-804\n\n## CWE-603: Use of Client-Side Authentication\n**Abstraction Level**: base\n**Similarity Score**: 3.64\n**Source**: graph\n\n**Description**:\nCWE-603: Use of Client-Side Authentication\n\n**Mapping Guidance**:\n- Usage: Allowed\n- Rationale: This CWE entry is at the Base level of abstraction, which is a preferred level of abstraction for mapping to the root causes of vulnerabilities.\n\n**Relationships**:\n- PEEROF -> CWE-656\n- PEEROF -> CWE-300\n- CHILDOF -> CWE-602\n- CHILDOF -> CWE-1390\n- PARENTOF -> CWE-603\n\n## CWE-321: Use of Hard-coded Cryptographic Key\n**Abstraction Level**: Variant\n**Similarity Score**: 3.02\n**Source**: graph\n\n**Description**:\nThe use of a hard-coded cryptographic key significantly increases the possibility that encrypted data may be recovered.\n\n**Mapping Guidance**:\n- Usage: Allowed\n- Rationale: This CWE entry is at the Variant level of abstraction, which is a preferred level of abstraction for mapping to the root causes of vulnerabilities.\n\n**Relationships**:\n- CANFOLLOW -> CWE-656\n- CHILDOF -> CWE-798\n- CHILDOF -> CWE-798\n- CHILDOF -> CWE-798\n- PARENTOF -> CWE-321\n\n## CWE-1272: Sensitive Information Uncleared Before Debug/Power State Transition\n**Abstraction Level**: base\n**Similarity Score**: 2.21\n**Source**: graph\n\n**Description**:\nCWE-1272: Sensitive Information Uncleared Before Debug/Power State Transition\n\n**Mapping Guidance**:\n- Usage: Allowed\n- Rationale: This CWE entry is at the Base level of abstraction, which is a preferred level of abstraction for mapping to the root causes of vulnerabilities.\n\n**Relationships**:\n- CANPRECEDE -> CWE-200\n- CHILDOF -> CWE-226\n- PARENTOF -> CWE-1272\n- CANFOLLOW -> CWE-1272\n\n## CWE-1291: Public Key Re-Use for Signing both Debug and Production Code\n**Abstraction Level**: base\n**Similarity Score**: 2.18\n**Source**: graph\n\n**Description**:\nCWE-1291: Public Key Re-Use for Signing both Debug and Production Code\n\n**Mapping Guidance**:\n- Usage: Allowed\n- Rationale: This CWE entry is at the Base level of abstraction, which is a preferred level of abstraction for mapping to the root causes of vulnerabilities.\n\n**Relationships**:\n- PEEROF -> CWE-321\n- CHILDOF -> CWE-693\n- PARENTOF -> CWE-1291\n\n## CWE-760: Use of a One-Way Hash with a Predictable Salt\n**Abstraction Level**: variant\n**Similarity Score**: 2.16\n**Source**: graph\n\n**Description**:\nCWE-760: Use of a One-Way Hash with a Predictable Salt\n\n**Mapping Guidance**:\n- Usage: Allowed\n- Rationale: This CWE entry is at the Variant level of abstraction, which is a preferred level of abstraction for mapping to the root causes of vulnerabilities.\n\n**Relationships**:\n- CHILDOF -> CWE-916\n- PARENTOF -> CWE-760\n\n## CWE-337: Predictable Seed in Pseudo-Random Number Generator (PRNG)\n**Abstraction Level**: variant\n**Similarity Score**: 2.16\n**Source**: graph\n\n**Description**:\nCWE-337: Predictable Seed in Pseudo-Random Number Generator (PRNG)\n\n**Mapping Guidance**:\n- Usage: Allowed\n- Rationale: This CWE entry is at the Variant level of abstraction, which is a preferred level of abstraction for mapping to the root causes of vulnerabilities.\n\n**Relationships**:\n- CHILDOF -> CWE-335\n- PARENTOF -> CWE\n\n\n## CWE Relationship Analysis\n\nCurrent CWEs represent these abstraction levels: .\n\n\n### Vulnerability Chain Analysis\n\n**Chain starting from CWE-798:**\n- 798 (Use of Hard-coded Credentials) - ROOT\n\n\n**Chain starting from CWE-259:**\n- 259 (Use of Hard-coded Password) - ROOT\n\n\n\n### CWE Relationship Diagram\n\n```mermaid\ngraph TD\n    classDef primary fill:#f96,stroke:#333,stroke-width:2px\n    classDef secondary fill:#69f,stroke:#333\n    classDef tertiary fill:#9e9,stroke:#333\n```",
  "criticism": "",
  "resolution": "",
  "relevant_cwes": [
    {
      "metadata": {
        "doc_id": "656",
        "name": "Reliance on Security Through Obscurity",
        "source": "sparse"
      },
      "similarity": 700.0
    },
    {
      "metadata": {
        "doc_id": "328",
        "name": "Use of Weak Hash",
        "source": "sparse"
      },
      "similarity": 305.02616056256943
    },
    {
      "metadata": {
        "doc_id": "330",
        "name": "Use of Insufficiently Random Values",
        "source": "sparse"
      },
      "similarity": 300.51150775290466
    },
    {
      "metadata": {
        "doc_id": "327",
        "name": "Use of a Broken or Risky Cryptographic Algorithm",
        "source": "sparse"
      },
      "similarity": 280.27133096379924
    },
    {
      "metadata": {
        "doc_id": "335",
        "name": "Incorrect Usage of Seeds in Pseudo-Random Number Generator (PRNG)",
        "source": "sparse"
      },
      "similarity": 278.7187306430474
    },
    {
      "metadata": {
        "doc_id": "337",
        "name": "Predictable Seed in Pseudo-Random Number Generator (PRNG)",
        "source": "sparse"
      },
      "similarity": 278.21579813610435
    },
    {
      "metadata": {
        "doc_id": "916",
        "name": "Use of Password Hash With Insufficient Computational Effort",
        "source": "sparse"
      },
      "similarity": 273.5634280149861
    },
    {
      "metadata": {
        "doc_id": "203",
        "name": "Observable Discrepancy",
        "source": "sparse"
      },
      "similarity": 257.62267332537294
    },
    {
      "metadata": {
        "doc_id": "760",
        "name": "Use of a One-Way Hash with a Predictable Salt",
        "type": "Variant",
        "original_content": "The product uses a one-way cryptographic hash against an input that should not be reversible, such as a password, but the product uses a predictable salt as part of the input.",
        "keyphrase_source": "rootcause:weak hashing algorithm",
        "source": "dense",
        "mapping_notes": {
          "usage": "Allowed",
          "rationale": "This CWE entry is at the Variant level of abstraction, which is a preferred level of abstraction for mapping to the root causes of vulnerabilities.",
          "comments": "Carefully read both the name and description to ensure that this mapping is an appropriate fit. Do not try to 'force' a mapping to a lower-level Base/Variant simply to comply with this preferred level of abstraction.",
          "reasons": [
            "Acceptable-Use"
          ]
        },
        "score_info": {
          "retrievers": [
            "dense",
            "graph"
          ],
          "retriever_count": 2,
          "normalized_scores": {
            "dense": 0.5304739394491538,
            "graph": 1.530355406130465
          }
        }
      },
      "similarity": 0.5304739394491538
    },
    {
      "doc_id": "321",
      "text": "The use of a hard-coded cryptographic key significantly increases the possibility that encrypted data may be recovered.",
      "score": 0.5983145548669425,
      "metadata": {
        "doc_id": "321",
        "name": "Use of Hard-coded Cryptographic Key",
        "type": "Variant",
        "extended_description": null,
        "alternate_terms": [],
        "original_content": "The use of a hard-coded cryptographic key significantly increases the possibility that encrypted data may be recovered.",
        "relationships": [
          {
            "source_id": "321",
            "target_id": "656",
            "label": "CANFOLLOW",
            "properties": {
              "view_id": "1000"
            }
          },
          {
            "source_id": "321",
            "target_id": "798",
            "label": "CHILDOF",
            "properties": {
              "ordinal": "Primary",
              "view_id": "1340"
            }
          },
          {
            "source_id": "321",
            "target_id": "798",
            "label": "CHILDOF",
            "properties": {
              "ordinal": "Primary",
              "view_id": "1305"
            }
          },
          {
            "source_id": "321",
            "target_id": "798",
            "label": "CHILDOF",
            "properties": {
              "ordinal": "Primary",
              "view_id": "1000"
            }
          },
          {
            "source_id": "798",
            "target_id": "321",
            "label": "PARENTOF",
            "properties": {
              "ordinal": "Primary",
              "view_id": "1000"
            }
          },
          {
            "source_id": "656",
            "target_id": "321",
            "label": "CANPRECEDE",
            "properties": {
              "view_id": "1000"
            }
          },
          {
            "source_id": "259",
            "target_id": "321",
            "label": "PEEROF",
            "properties": {
              "view_id": "1000"
            }
          },
          {
            "source_id": "1291",
            "target_id": "321",
            "label": "PEEROF",
            "properties": {
              "ordinal": "Primary",
              "view_id": "1000"
            }
          }
        ],
        "source": "graph",
        "sources": [
          "vector",
          "graph"
        ],
        "vector_score": 0.5983145548669425,
        "graph_score": 3.7507200000000003,
        "score_components": {
          "relationship_chain": 1.0,
          "explicit_mention": 1.0,
          "abstraction_path": 0.6080000000000001,
          "sequence_path": 1.0
        },
        "abstraction_factor": 1.2,
        "graph_path_info": {
          "path_types": [
            "relationship_chain",
            "abstraction_path_down",
            "vulnerability_sequence_forward"
          ],
          "best_paths": {
            "relationship_chain": {
              "path": [
                [
                  "656",
                  "321",
                  "CANPRECEDE"
                ]
              ],
              "score": 1.0,
              "type": "relationship_chain",
              "source": "656"
            },
            "abstraction_path_down": {
              "path": [
                [
                  "1391",
                  "798",
                  "PARENTOF"
                ],
                [
                  "798",
                  "321",
                  "PARENTOF"
                ]
              ],
              "score": 0.6080000000000001,
              "type": "abstraction_path_down",
              "source": "1391"
            },
            "vulnerability_sequence_forward": {
              "path": [
                [
                  "656",
                  "321",
                  "CANPRECEDE"
                ]
              ],
              "score": 1.0,
              "type": "vulnerability_sequence_forward",
              "source": "656"
            }
          }
        },
        "is_explicit": true,
        "abstraction_level": "variant",
        "position": "after",
        "mapping_notes": {
          "usage": "Allowed",
          "rationale": "This CWE entry is at the Variant level of abstraction, which is a preferred level of abstraction for mapping to the root causes of vulnerabilities.",
          "comments": "Carefully read both the name and description to ensure that this mapping is an appropriate fit. Do not try to 'force' a mapping to a lower-level Base/Variant simply to comply with this preferred level of abstraction.",
          "reasons": [
            "Acceptable-Use"
          ]
        },
        "score_info": {
          "retrievers": [
            "dense",
            "graph"
          ],
          "retriever_count": 2,
          "normalized_scores": {
            "dense": 0.5164527127288678,
            "graph": 2.489757821946777
          }
        }
      },
      "similarity": 2.489757821946777
    }
  ],
  "identified_cwes": {
    "analyzer": [
      "CWE-798",
      "CWE-259",
      "CWE-916",
      "CWE-257",
      "CWE-1391",
      "CWE-345",
      "CWE-327",
      "CWE-804",
      "CWE-226",
      "CWE-1272",
      "CWE-337",
      "CWE-328",
      "CWE-338",
      "CWE-200",
      "CWE-693",
      "CWE-602",
      "CWE-656",
      "CWE-603",
      "CWE-335",
      "CWE-384",
      "CWE-1291",
      "CWE-471",
      "CWE-300",
      "CWE-1390",
      "CWE-472",
      "CWE-330",
      "CWE-642",
      "CWE-326",
      "CWE-1240",
      "CWE-760",
      "CWE-331",
      "CWE-321",
      "CWE-863"
    ],
    "critic_additional": []
  }
}