{
  "cve_id": "CVE-2025-5389",
  "description": "A vulnerability, which was classified as critical, has been found in JeeWMS up to 20250504. Affected by this issue is the function dogenerateOne2Many of the file /generateController.do?dogenerateOne2Many of the component File Handler. The manipulation leads to **improper access controls**. The attack may be launched remotely. Continious delivery with rolling releases is used by this product. Therefore, no version details of affected nor updated releases are available.",
  "key_phrases": {
    "rootcause": "",
    "weakness": "improper access controls",
    "impact": "",
    "vector": "",
    "attacker": "",
    "product": "JeeWMS",
    "version": "up to 20250504",
    "component": "/generateController.do?dogenerateOne2Many"
  },
  "reference_content": "## Analysis of CVE-2025-5389 Content (gitee.com_4fcc10a4_20250624_150117.html)\n\nThis content **IS RELATED** to a set of vulnerabilities, though it doesn't directly reference CVE-2025-5389. It details multiple vulnerabilities found in the JeeWMS application hosted on Gitee. The content provides more detail than a typical CVE description would.\n\nHere's a breakdown of the extracted information:\n\n**Root cause of vulnerability:**\n\nThe root causes vary depending on the vulnerability, including:\n\n*   **SQL Injection:** Improper input sanitization allowing malicious SQL code execution.\n*   **Path Traversal:** Insufficient validation of file paths, enabling access to arbitrary files.\n*   **Arbitrary File Read:** Lack of proper access controls allowing reading of any file.\n*   **Arbitrary File Write:** Lack of proper access controls allowing writing to any file.\n*   **Remote Code Execution (RCE):** Ability to write controllable JSP files to arbitrary locations, leading to code execution.\n\n**Weaknesses/vulnerabilities present:**\n\n*   SQL Injection (in `CgAutoListController.do?datagrid` and `cgformTransController.do?transEditor`, `GenerateController.do?dogenerate`)\n*   Path Traversal (in `cgformTemplateController.do?doAdd`)\n*   Arbitrary File Read (in `cgformTemplateController.do?showPic`)\n*   Arbitrary File Write (in `GenerateController.do?dogenerate`, `GenerateController.do?dogenerateOne2Many`, `systemController/filedeal.do`)\n*   Remote Code Execution (RCE) (in `GenerateController.do?dogenerate`, `GenerateController.do?dogenerateOne2Many`)\n\n**Impact of exploitation:**\n\n*   **SQL Injection:** Data breach, data manipulation, potential system compromise.\n*   **Path Traversal:** Unauthorized access to sensitive files, potential system compromise.\n*   **Arbitrary File Read:** Exposure of sensitive information.\n*   **Arbitrary File Write:**  Overwriting critical system files, potential system compromise.\n*   **Remote Code Execution (RCE):** Complete system compromise, allowing attackers to execute arbitrary code on the server.\n\n**Attack vectors:**\n\n*   HTTP requests to specific controller methods with crafted parameters.  The specific request paths are provided for each vulnerability.\n\n**Required attacker capabilities/position:**\n\n*   Unauthenticated attacker (likely, as no authentication is mentioned as a prerequisite for exploitation in the provided text).\n*   Ability to send HTTP requests to the JeeWMS application.\n*   Knowledge of the vulnerable request paths and parameters.\n\n**Mitigation or fix:**\n\nThe content does *not* provide specific mitigation or fix details. It states that the vulnerability details and PoCs have been sent to the vendor (huayi-tec.com) via email.",
  "similar_info": {
    "cwe_distribution": {},
    "cwe_consensus": "",
    "similarity_stats": {
      "thresholds": [],
      "total_samples_by_threshold": {},
      "top_cwes_by_threshold": {}
    }
  },
  "similarity_summary": {
    "consensus_cwe": "",
    "top_cwes": [],
    "confidence_levels": {},
    "total_samples": 0
  },
  "analysis": "# Summary\n| CWE ID  | CWE Name                                                                   | Confidence | CWE Abstraction Level | CWE Vulnerability Mapping Label | CWE-Vulnerability Mapping Notes |\n| :-------- | :------------------------------------------------------------------------- | :---------- | :---------------------- | :------------------------------ | :------------------------------ |\n| CWE-285   | Improper Authorization                                                      | 0.8        | Class                   | Primary                         | Allowed-with-Review             |\n| CWE-863   | Incorrect Authorization                                                     | 0.7        | Base                    | Secondary                       | Allowed-with-Review             |\n| CWE-552   | Files or Directories Accessible to External Parties                         | 0.6        | Base                    | Secondary                       | Allowed                         |\n\n## Evidence and Confidence\n\n*   **Confidence Score:** 0.8\n*   **Evidence Strength:** MEDIUM\n\n## Relationship Analysis\n\nThe primary CWE is CWE-285, which is a class-level CWE. It has child CWEs like CWE-863 (Incorrect Authorization) and CWE-862 (Missing Authorization) that are more specific. Since the vulnerability description specifies **improper access controls**, CWE-863 is a good fit as a secondary CWE since it's more specific than CWE-285, although the description does not provide the specifics to make it the primary. CWE-552 is a peer that could arise from the improper authorization. The abstraction levels influenced the selection, favoring the most specific and relevant option.\n\n```mermaid\ngraph TD\n    cwe285[\"CWE-285: Improper Authorization\"]\n    cwe863[\"CWE-863: Incorrect Authorization\"]\n    cwe862[\"CWE-862: Missing Authorization\"]\n    cwe552[\"CWE-552: Files or Directories Accessible to External Parties\"]\n\n    cwe863 -->|CHILDOF| cwe285\n    cwe862 -->|CHILDOF| cwe285\n    cwe552 -->|PEEROF| cwe285\n\n    classDef primary fill:#f96,stroke:#333,stroke-width:2px\n    classDef secondary fill:#69f,stroke:#333\n    class cwe285 primary\n    class cwe863,cwe552 secondary\n```\n\n## Vulnerability Chain\n\nThe chain of events is as follows:\n1.  The root cause is **improper access controls** (CWE-285).\n2.  This leads to incorrect authorization (CWE-863).\n3.  The impact is that files or directories become accessible to external parties (CWE-552).\n\n## Summary of Analysis\n\nThe initial assessment focused on **improper access controls** as the root cause. The analysis considered CWE-285 (Improper Authorization) as the primary candidate, with CWE-863 (Incorrect Authorization) and CWE-552 (Files or Directories Accessible to External Parties) as secondary candidates.\n\nThe evidence from the vulnerability description and the CVE Reference Links Content Summary support this assessment. The description explicitly mentions **improper access controls**, which aligns with CWE-285. The supporting CVE content mentions arbitrary file read/write due to a lack of proper access controls, which directly relates to CWE-552.\n\n> \"Affected by this issue is the function dogenerateOne2Many of the file /generateController.do?dogenerateOne2Many of the component File Handler. The manipulation leads to **improper access controls**.\"\n\nThe graph relationships influenced the selection by guiding the analysis towards more specific child CWEs of CWE-285. While CWE-285 is a class-level CWE, the specific context of the vulnerability (file handling with **improper access controls**) justifies including CWE-863 and CWE-552 to represent the root cause and the potential impact.\n\nThe selected CWEs are at an appropriate level of specificity. CWE-285 captures the general authorization issue, while CWE-863 represents the specific incorrect authorization and CWE-552 describes the impact of the vulnerability.\n\nRelevant CWE Information:\n\n# Enhanced Context (25 CWEs)\n\n## CWE-73: External Control of File Name or Path\n**Abstraction Level**: Base\n**Similarity Score**: 0.81\n**Source**: dense\n\n**Description**:\nThe product allows user input to control or influence paths or file names that are used in filesystem operations.\n\n**Mapping Guidance**:\n- Usage: Allowed\n- Rationale: This CWE entry is at the Base level of abstraction, which is a preferred level of abstraction for mapping to the root causes of vulnerabilities.\n\n## CWE-41: Improper Resolution of Path Equivalence\n**Abstraction Level**: Base\n**Similarity Score**: 0.80\n**Source**: dense\n\n**Description**:\nThe product is vulnerable to file system contents disclosure through path equivalence. Path equivalence involves the use of special characters in file and directory names. The associated manipulations are intended to generate multiple names for the same object.\n\n**Mapping Guidance**:\n- Usage: Allowed\n- Rationale: This CWE entry is at the Base level of abstraction, which is a preferred level of abstraction for mapping to the root causes of vulnerabilities.\n\n## CWE-23: Relative Path Traversal\n**Abstraction Level**: Base\n**Similarity Score**: 0.79\n**Source**: dense\n\n**Description**:\nThe product uses external input to construct a pathname that should be within a restricted directory, but it does not properly neutralize sequences such as \"..\" that can resolve to a location that is outside of that directory.\n\n**Mapping Guidance**:\n- Usage: Allowed\n- Rationale: This CWE entry is at the Base level of abstraction, which is a preferred level of abstraction for mapping to the root causes of vulnerabilities.\n\n## CWE-610: Externally Controlled Reference to a Resource in Another Sphere\n**Abstraction Level**: Class\n**Similarity Score**: 0.79\n**Source**: dense\n\n**Description**:\nThe product uses an externally controlled name or reference that resolves to a resource that is outside of the intended control sphere.\n\n**Mapping Guidance**:\n- Usage: Discouraged\n- Rationale: This CWE entry is a level-1 Class (i.e., a child of a Pillar). It might have lower-level children that would be more appropriate\n\n## CWE-668: Exposure of Resource to Wrong Sphere\n**Abstraction Level**: Class\n**Similarity Score**: 0.79\n**Source**: dense\n\n**Description**:\nThe product exposes a resource to the wrong control sphere, providing unintended actors with inappropriate access to the resource.\n\n**Mapping Guidance**:\n- Usage: Discouraged\n- Rationale: CWE-668 is high-level and is often misused as a catch-all when lower-level CWE IDs might be applicable. It is sometimes used for low-information vulnerability reports [REF-1287]. It is a level-1 Class (i.e., a child of a Pillar). It is not useful for trend analysis.\n\n## CWE-552: Files or Directories Accessible to External Parties\n**Abstraction Level**: Base\n**Similarity Score**: 0.79\n**Source**: dense\n\n**Description**:\nThe product makes files or directories accessible to unauthorized actors, even though they should not be.\n\n**Mapping Guidance**:\n- Usage: Allowed\n- Rationale: This CWE entry is at the Base level of abstraction, which is a preferred level of abstraction for mapping to the root causes of vulnerabilities.\n\n## CWE-74: Improper Neutralization of Special Elements in Output Used by a Downstream Component ('Injection')\n**Abstraction Level**: Class\n**Similarity Score**: 0.78\n**Source**: dense\n\n**Description**:\nThe product constructs all or part of a command, data structure, or record using externally-influenced input from an upstream component, but it does not neutralize or incorrectly neutralizes special elements that could modify how it is parsed or interpreted when it is sent to a downstream component.\n\n**Mapping Guidance**:\n- Usage: Discouraged\n- Rationale: CWE-74 is high-level and often misused when lower-level weaknesses are more appropriate.\n\n## CWE-99: Improper Control of Resource Identifiers ('Resource Injection')\n**Abstraction Level**: Class\n**Similarity Score**: 0.78\n**Source**: dense\n\n**Description**:\nThe product receives input from an upstream component, but it does not restrict or incorrectly restricts the input before it is used as an identifier for a resource that may be outside the intended sphere of control.\n\n**Mapping Guidance**:\n- Usage: Allowed-with-Review\n- Rationale: This CWE entry is a Class and might have Base-level children that would be more appropriate\n\n## CWE-59: Improper Link Resolution Before File Access ('Link Following')\n**Abstraction Level**: Base\n**Similarity Score**: 0.77\n**Source**: dense\n\n**Description**:\nThe product attempts to access a file based on the filename, but it does not properly prevent that filename from identifying a link or shortcut that resolves to an unintended resource.\n\n**Mapping Guidance**:\n- Usage: Allowed\n- Rationale: This CWE entry is at the Base level of abstraction, which is a preferred level of abstraction for mapping to the root causes of vulnerabilities.\n\n## CWE-404: Improper Resource Shutdown or Release\n**Abstraction Level**: Class\n**Similarity Score**: 0.77\n**Source**: dense\n\n**Description**:\nThe product does not release or incorrectly releases a resource before it is made available for re-use.\n\n**Mapping Guidance**:\n- Usage: Allowed-with-Review\n- Rationale: This CWE entry is a Class and might have Base-level children that would be more appropriate\n\n## CWE-79: Improper Neutralization of Input During Web Page Generation ('Cross-site Scripting')\n**Abstraction Level**: Base\n**Similarity Score**: 7121.92\n**Source**: sparse\n\n**Description**:\nThe product does not neutralize or incorrectly neutralizes user-controllable input before it is placed in output that is used as a web page that is served to other users.\n\n**Mapping Guidance**:\n- Usage: Allowed\n- Rationale: This CWE entry is at the Base level of abstraction, which is a preferred level of abstraction for mapping to the root causes of vulnerabilities.\n\n## CWE-434: Unrestricted Upload of File with Dangerous Type\n**Abstraction Level**: Base\n**Similarity Score**: 6790.06\n**Source**: sparse\n\n**Description**:\nThe product allows the upload or transfer of dangerous file types that are automatically processed within its environment.\n\n**Mapping Guidance**:\n- Usage: Allowed\n- Rationale: This CWE entry is at the Base level of abstraction, which is a preferred level of abstraction for mapping to the root causes of vulnerabilities.\n\n## CWE-22: Improper Limitation of a Pathname to a Restricted Directory ('Path Traversal')\n**Abstraction Level**: Base\n**Similarity Score**: 6762.10\n**Source**: sparse\n\n**Description**:\nThe product uses external input to construct a pathname that is intended to identify a file or directory that is located underneath a restricted parent directory, but the product does not properly neutralize special elements within the pathname that can cause the pathname to resolve to a location that is outside of the restricted directory.\n\n**Mapping Guidance**:\n- Usage: Allowed\n- Rationale: This CWE entry is at the Base level of abstraction, which is a preferred level of abstraction for mapping to the root causes of vulnerabilities.\n\n## CWE-116: Improper Encoding or Escaping of Output\n**Abstraction Level**: Class\n**Similarity Score**: 6720.37\n**Source**: sparse\n\n**Description**:\nThe product prepares a structured message for communication with another component, but encoding or escaping of the data is either missing or done incorrectly. As a result, the intended structure of the message is not preserved.\n\n**Mapping Guidance**:\n- Usage: Allowed-with-Review\n- Rationale: This CWE entry is a Class and might have Base-level children that would be more appropriate\n\n## CWE-863: Incorrect Authorization\n**Abstraction Level**: Class\n**Similarity Score**: 6655.35\n**Source**: sparse\n\n**Description**:\nThe product performs an authorization check when an actor attempts to access a resource or perform an action, but it does not correctly perform the check.\n\n**Mapping Guidance**:\n- Usage: Allowed-with-Review\n- Rationale: This CWE entry is a Class and might have Base-level children that would be more appropriate\n\n## CWE-79: Improper Neutralization of Input During Web Page Generation ('Cross-site Scripting')\n**Abstraction Level**: base\n**Similarity Score**: 5.03\n**Source**: graph\n\n**Description**:\nCWE-79: Improper Neutralization of Input During Web Page Generation ('Cross-site Scripting')\n\n**Mapping Guidance**:\n- Usage: Allowed\n- Rationale: This CWE entry is at the Base level of abstraction, which is a preferred level of abstraction for mapping to the root causes of vulnerabilities.\n\n**Relationships**:\n- PARENTOF -> CWE-87\n- PARENTOF -> CWE-86\n- PARENTOF -> CWE-85\n- PARENTOF -> CWE-84\n- PARENTOF -> CWE-83\n\n## CWE-183: Permissive List of Allowed Inputs\n**Abstraction Level**: base\n**Similarity Score**: 4.82\n**Source**: graph\n\n**Description**:\nCWE-183: Permissive List of Allowed Inputs\n\n**Mapping Guidance**:\n- Usage: Allowed\n- Rationale: This CWE entry is at the Base level of abstraction, which is a preferred level of abstraction for mapping to the root causes of vulnerabilities.\n\n**Relationships**:\n- PARENTOF -> CWE-942\n- CANPRECEDE -> CWE-434\n- CHILDOF -> CWE-697\n- CHILDOF -> CWE-183\n- PARENTOF -> CWE-183\n\n## CWE-494: Download of Code Without Integrity Check\n**Abstraction Level**: base\n**Similarity Score**: 4.33\n**Source**: graph\n\n**Description**:\nCWE-494: Download of Code Without Integrity Check\n\n**Mapping Guidance**:\n- Usage: Allowed\n- Rationale: This CWE entry is at the Base level of abstraction, which is a preferred level of abstraction for mapping to the root causes of vulnerabilities.\n\n**Relationships**:\n- CANFOLLOW -> CWE-79\n- CHILDOF -> CWE-669\n- CHILDOF -> CWE-669\n- CHILDOF -> CWE-345\n- CANPRECEDE -> CWE-494\n\n## CWE-22: Improper Limitation of a Pathname to a Restricted Directory ('Path Traversal')\n**Abstraction Level**: base\n**Similarity Score**: 4.33\n**Source**: graph\n\n**Description**:\nCWE-22: Improper Limitation of a Pathname to a Restricted Directory ('Path Traversal')\n\n**Mapping Guidance**:\n- Usage: Allowed\n- Rationale: This CWE entry is at the Base level of abstraction, which is a preferred level of abstraction for mapping to the root causes of vulnerabilities.\n\n**Relationships**:\n- CANFOLLOW -> CWE-73\n- PARENTOF -> CWE-36\n- PARENTOF -> CWE-23\n- CANFOLLOW -> CWE-20\n- CANFOLLOW -> CWE-172\n\n## CWE-619: Dangling Database Cursor ('Cursor Injection')\n**Abstraction Level**: base\n**Similarity Score**: 4.33\n**Source**: graph\n\n**Description**:\nCWE-619: Dangling Database Cursor ('Cursor Injection')\n\n**Mapping Guidance**:\n- Usage: Allowed\n- Rationale: This CWE entry is at the Base level of abstraction, which is a preferred level of abstraction for mapping to the root causes of vulnerabilities.\n\n**Relationships**:\n- CANFOLLOW -> CWE-404\n- CHILDOF -> CWE-402\n- CANPRECEDE -> CWE-619\n- PARENTOF -> CWE-619\n\n## CWE-98: Improper Control of Filename for Include/Require Statement in PHP Program ('PHP Remote File Inclusion')\n**Abstraction Level**: variant\n**Similarity Score**: 3.88\n**Source**: graph\n\n**Description**:\nCWE-98: Improper Control of Filename for Include/Require Statement in PHP Program ('PHP Remote File Inclusion')\n\n**Mapping Guidance**:\n- Usage: Allowed\n- Rationale: This CWE entry is at the Variant level of abstraction, which is a preferred level of abstraction for mapping to the root causes of vulnerabilities.\n\n**Relationships**:\n- CANFOLLOW -> CWE-73\n- CANFOLLOW -> CWE-473\n- CANFOLLOW -> CWE-456\n- CANFOLLOW -> CWE-425\n- CANFOLLOW -> CWE-184\n\n## CWE-351: Insufficient Type Distinction\n**Abstraction Level**: base\n**Similarity Score**: 3.64\n**Source**: graph\n\n**Description**:\nCWE-351: Insufficient Type Distinction\n\n**Mapping Guidance**:\n- Usage: Allowed\n- Rationale: This CWE entry is at the Base level of abstraction, which is a preferred level of abstraction for mapping to the root causes of vulnerabilities.\n\n**Relationships**:\n- PEEROF -> CWE-436\n- CHILDOF -> CWE-345\n- PEEROF -> CWE-351\n- PARENTOF -> CWE-351\n\n## CWE-430: Deployment of Wrong Handler\n**Abstraction Level**: base\n**Similarity Score**: 3.64\n**Source**: graph\n\n**Description**:\nCWE-430: Deployment of Wrong Handler\n\n**Mapping Guidance**:\n- Usage: Allowed\n- Rationale: This CWE entry is at the Base level of abstraction, which is a preferred level of abstraction for mapping to the root causes of vulnerabilities.\n\n**Relationships**:\n- PEEROF -> CWE-434\n- CANPRECEDE -> CWE-433\n- CHILDOF -> CWE-691\n- PARENTOF -> CWE-430\n- PEEROF -> CWE-430\n\n## CWE-266: Incorrect Privilege Assignment\n**Abstraction Level**: base\n**Similarity Score**: 3.64\n**Source**: graph\n\n**Description**:\nCWE-266: Incorrect Privilege Assignment\n\n**Mapping Guidance**:\n- Usage: Allowed\n- Rationale: This CWE entry is at the Base level of abstraction, which is a preferred level of abstraction for mapping to the root causes of vulnerabilities.\n\n**Relationships**:\n- PARENTOF -> CWE-9\n- PARENTOF -> CWE-556\n- PARENTOF -> CWE-520\n- PARENTOF -> CWE-1022\n-",
  "analysis_with_relationships": "# Summary\n| CWE ID  | CWE Name                                                                   | Confidence | CWE Abstraction Level | CWE Vulnerability Mapping Label | CWE-Vulnerability Mapping Notes |\n| :-------- | :------------------------------------------------------------------------- | :---------- | :---------------------- | :------------------------------ | :------------------------------ |\n| CWE-285   | Improper Authorization                                                      | 0.8        | Class                   | Primary                         | Allowed-with-Review             |\n| CWE-863   | Incorrect Authorization                                                     | 0.7        | Base                    | Secondary                       | Allowed-with-Review             |\n| CWE-552   | Files or Directories Accessible to External Parties                         | 0.6        | Base                    | Secondary                       | Allowed                         |\n\n## Evidence and Confidence\n\n*   **Confidence Score:** 0.8\n*   **Evidence Strength:** MEDIUM\n\n## Relationship Analysis\n\nThe primary CWE is CWE-285, which is a class-level CWE. It has child CWEs like CWE-863 (Incorrect Authorization) and CWE-862 (Missing Authorization) that are more specific. Since the vulnerability description specifies **improper access controls**, CWE-863 is a good fit as a secondary CWE since it's more specific than CWE-285, although the description does not provide the specifics to make it the primary. CWE-552 is a peer that could arise from the improper authorization. The abstraction levels influenced the selection, favoring the most specific and relevant option.\n\n```mermaid\ngraph TD\n    cwe285[\"CWE-285: Improper Authorization\"]\n    cwe863[\"CWE-863: Incorrect Authorization\"]\n    cwe862[\"CWE-862: Missing Authorization\"]\n    cwe552[\"CWE-552: Files or Directories Accessible to External Parties\"]\n\n    cwe863 -->|CHILDOF| cwe285\n    cwe862 -->|CHILDOF| cwe285\n    cwe552 -->|PEEROF| cwe285\n\n    classDef primary fill:#f96,stroke:#333,stroke-width:2px\n    classDef secondary fill:#69f,stroke:#333\n    class cwe285 primary\n    class cwe863,cwe552 secondary\n```\n\n## Vulnerability Chain\n\nThe chain of events is as follows:\n1.  The root cause is **improper access controls** (CWE-285).\n2.  This leads to incorrect authorization (CWE-863).\n3.  The impact is that files or directories become accessible to external parties (CWE-552).\n\n## Summary of Analysis\n\nThe initial assessment focused on **improper access controls** as the root cause. The analysis considered CWE-285 (Improper Authorization) as the primary candidate, with CWE-863 (Incorrect Authorization) and CWE-552 (Files or Directories Accessible to External Parties) as secondary candidates.\n\nThe evidence from the vulnerability description and the CVE Reference Links Content Summary support this assessment. The description explicitly mentions **improper access controls**, which aligns with CWE-285. The supporting CVE content mentions arbitrary file read/write due to a lack of proper access controls, which directly relates to CWE-552.\n\n> \"Affected by this issue is the function dogenerateOne2Many of the file /generateController.do?dogenerateOne2Many of the component File Handler. The manipulation leads to **improper access controls**.\"\n\nThe graph relationships influenced the selection by guiding the analysis towards more specific child CWEs of CWE-285. While CWE-285 is a class-level CWE, the specific context of the vulnerability (file handling with **improper access controls**) justifies including CWE-863 and CWE-552 to represent the root cause and the potential impact.\n\nThe selected CWEs are at an appropriate level of specificity. CWE-285 captures the general authorization issue, while CWE-863 represents the specific incorrect authorization and CWE-552 describes the impact of the vulnerability.\n\nRelevant CWE Information:\n\n# Enhanced Context (25 CWEs)\n\n## CWE-73: External Control of File Name or Path\n**Abstraction Level**: Base\n**Similarity Score**: 0.81\n**Source**: dense\n\n**Description**:\nThe product allows user input to control or influence paths or file names that are used in filesystem operations.\n\n**Mapping Guidance**:\n- Usage: Allowed\n- Rationale: This CWE entry is at the Base level of abstraction, which is a preferred level of abstraction for mapping to the root causes of vulnerabilities.\n\n## CWE-41: Improper Resolution of Path Equivalence\n**Abstraction Level**: Base\n**Similarity Score**: 0.80\n**Source**: dense\n\n**Description**:\nThe product is vulnerable to file system contents disclosure through path equivalence. Path equivalence involves the use of special characters in file and directory names. The associated manipulations are intended to generate multiple names for the same object.\n\n**Mapping Guidance**:\n- Usage: Allowed\n- Rationale: This CWE entry is at the Base level of abstraction, which is a preferred level of abstraction for mapping to the root causes of vulnerabilities.\n\n## CWE-23: Relative Path Traversal\n**Abstraction Level**: Base\n**Similarity Score**: 0.79\n**Source**: dense\n\n**Description**:\nThe product uses external input to construct a pathname that should be within a restricted directory, but it does not properly neutralize sequences such as \"..\" that can resolve to a location that is outside of that directory.\n\n**Mapping Guidance**:\n- Usage: Allowed\n- Rationale: This CWE entry is at the Base level of abstraction, which is a preferred level of abstraction for mapping to the root causes of vulnerabilities.\n\n## CWE-610: Externally Controlled Reference to a Resource in Another Sphere\n**Abstraction Level**: Class\n**Similarity Score**: 0.79\n**Source**: dense\n\n**Description**:\nThe product uses an externally controlled name or reference that resolves to a resource that is outside of the intended control sphere.\n\n**Mapping Guidance**:\n- Usage: Discouraged\n- Rationale: This CWE entry is a level-1 Class (i.e., a child of a Pillar). It might have lower-level children that would be more appropriate\n\n## CWE-668: Exposure of Resource to Wrong Sphere\n**Abstraction Level**: Class\n**Similarity Score**: 0.79\n**Source**: dense\n\n**Description**:\nThe product exposes a resource to the wrong control sphere, providing unintended actors with inappropriate access to the resource.\n\n**Mapping Guidance**:\n- Usage: Discouraged\n- Rationale: CWE-668 is high-level and is often misused as a catch-all when lower-level CWE IDs might be applicable. It is sometimes used for low-information vulnerability reports [REF-1287]. It is a level-1 Class (i.e., a child of a Pillar). It is not useful for trend analysis.\n\n## CWE-552: Files or Directories Accessible to External Parties\n**Abstraction Level**: Base\n**Similarity Score**: 0.79\n**Source**: dense\n\n**Description**:\nThe product makes files or directories accessible to unauthorized actors, even though they should not be.\n\n**Mapping Guidance**:\n- Usage: Allowed\n- Rationale: This CWE entry is at the Base level of abstraction, which is a preferred level of abstraction for mapping to the root causes of vulnerabilities.\n\n## CWE-74: Improper Neutralization of Special Elements in Output Used by a Downstream Component ('Injection')\n**Abstraction Level**: Class\n**Similarity Score**: 0.78\n**Source**: dense\n\n**Description**:\nThe product constructs all or part of a command, data structure, or record using externally-influenced input from an upstream component, but it does not neutralize or incorrectly neutralizes special elements that could modify how it is parsed or interpreted when it is sent to a downstream component.\n\n**Mapping Guidance**:\n- Usage: Discouraged\n- Rationale: CWE-74 is high-level and often misused when lower-level weaknesses are more appropriate.\n\n## CWE-99: Improper Control of Resource Identifiers ('Resource Injection')\n**Abstraction Level**: Class\n**Similarity Score**: 0.78\n**Source**: dense\n\n**Description**:\nThe product receives input from an upstream component, but it does not restrict or incorrectly restricts the input before it is used as an identifier for a resource that may be outside the intended sphere of control.\n\n**Mapping Guidance**:\n- Usage: Allowed-with-Review\n- Rationale: This CWE entry is a Class and might have Base-level children that would be more appropriate\n\n## CWE-59: Improper Link Resolution Before File Access ('Link Following')\n**Abstraction Level**: Base\n**Similarity Score**: 0.77\n**Source**: dense\n\n**Description**:\nThe product attempts to access a file based on the filename, but it does not properly prevent that filename from identifying a link or shortcut that resolves to an unintended resource.\n\n**Mapping Guidance**:\n- Usage: Allowed\n- Rationale: This CWE entry is at the Base level of abstraction, which is a preferred level of abstraction for mapping to the root causes of vulnerabilities.\n\n## CWE-404: Improper Resource Shutdown or Release\n**Abstraction Level**: Class\n**Similarity Score**: 0.77\n**Source**: dense\n\n**Description**:\nThe product does not release or incorrectly releases a resource before it is made available for re-use.\n\n**Mapping Guidance**:\n- Usage: Allowed-with-Review\n- Rationale: This CWE entry is a Class and might have Base-level children that would be more appropriate\n\n## CWE-79: Improper Neutralization of Input During Web Page Generation ('Cross-site Scripting')\n**Abstraction Level**: Base\n**Similarity Score**: 7121.92\n**Source**: sparse\n\n**Description**:\nThe product does not neutralize or incorrectly neutralizes user-controllable input before it is placed in output that is used as a web page that is served to other users.\n\n**Mapping Guidance**:\n- Usage: Allowed\n- Rationale: This CWE entry is at the Base level of abstraction, which is a preferred level of abstraction for mapping to the root causes of vulnerabilities.\n\n## CWE-434: Unrestricted Upload of File with Dangerous Type\n**Abstraction Level**: Base\n**Similarity Score**: 6790.06\n**Source**: sparse\n\n**Description**:\nThe product allows the upload or transfer of dangerous file types that are automatically processed within its environment.\n\n**Mapping Guidance**:\n- Usage: Allowed\n- Rationale: This CWE entry is at the Base level of abstraction, which is a preferred level of abstraction for mapping to the root causes of vulnerabilities.\n\n## CWE-22: Improper Limitation of a Pathname to a Restricted Directory ('Path Traversal')\n**Abstraction Level**: Base\n**Similarity Score**: 6762.10\n**Source**: sparse\n\n**Description**:\nThe product uses external input to construct a pathname that is intended to identify a file or directory that is located underneath a restricted parent directory, but the product does not properly neutralize special elements within the pathname that can cause the pathname to resolve to a location that is outside of the restricted directory.\n\n**Mapping Guidance**:\n- Usage: Allowed\n- Rationale: This CWE entry is at the Base level of abstraction, which is a preferred level of abstraction for mapping to the root causes of vulnerabilities.\n\n## CWE-116: Improper Encoding or Escaping of Output\n**Abstraction Level**: Class\n**Similarity Score**: 6720.37\n**Source**: sparse\n\n**Description**:\nThe product prepares a structured message for communication with another component, but encoding or escaping of the data is either missing or done incorrectly. As a result, the intended structure of the message is not preserved.\n\n**Mapping Guidance**:\n- Usage: Allowed-with-Review\n- Rationale: This CWE entry is a Class and might have Base-level children that would be more appropriate\n\n## CWE-863: Incorrect Authorization\n**Abstraction Level**: Class\n**Similarity Score**: 6655.35\n**Source**: sparse\n\n**Description**:\nThe product performs an authorization check when an actor attempts to access a resource or perform an action, but it does not correctly perform the check.\n\n**Mapping Guidance**:\n- Usage: Allowed-with-Review\n- Rationale: This CWE entry is a Class and might have Base-level children that would be more appropriate\n\n## CWE-79: Improper Neutralization of Input During Web Page Generation ('Cross-site Scripting')\n**Abstraction Level**: base\n**Similarity Score**: 5.03\n**Source**: graph\n\n**Description**:\nCWE-79: Improper Neutralization of Input During Web Page Generation ('Cross-site Scripting')\n\n**Mapping Guidance**:\n- Usage: Allowed\n- Rationale: This CWE entry is at the Base level of abstraction, which is a preferred level of abstraction for mapping to the root causes of vulnerabilities.\n\n**Relationships**:\n- PARENTOF -> CWE-87\n- PARENTOF -> CWE-86\n- PARENTOF -> CWE-85\n- PARENTOF -> CWE-84\n- PARENTOF -> CWE-83\n\n## CWE-183: Permissive List of Allowed Inputs\n**Abstraction Level**: base\n**Similarity Score**: 4.82\n**Source**: graph\n\n**Description**:\nCWE-183: Permissive List of Allowed Inputs\n\n**Mapping Guidance**:\n- Usage: Allowed\n- Rationale: This CWE entry is at the Base level of abstraction, which is a preferred level of abstraction for mapping to the root causes of vulnerabilities.\n\n**Relationships**:\n- PARENTOF -> CWE-942\n- CANPRECEDE -> CWE-434\n- CHILDOF -> CWE-697\n- CHILDOF -> CWE-183\n- PARENTOF -> CWE-183\n\n## CWE-494: Download of Code Without Integrity Check\n**Abstraction Level**: base\n**Similarity Score**: 4.33\n**Source**: graph\n\n**Description**:\nCWE-494: Download of Code Without Integrity Check\n\n**Mapping Guidance**:\n- Usage: Allowed\n- Rationale: This CWE entry is at the Base level of abstraction, which is a preferred level of abstraction for mapping to the root causes of vulnerabilities.\n\n**Relationships**:\n- CANFOLLOW -> CWE-79\n- CHILDOF -> CWE-669\n- CHILDOF -> CWE-669\n- CHILDOF -> CWE-345\n- CANPRECEDE -> CWE-494\n\n## CWE-22: Improper Limitation of a Pathname to a Restricted Directory ('Path Traversal')\n**Abstraction Level**: base\n**Similarity Score**: 4.33\n**Source**: graph\n\n**Description**:\nCWE-22: Improper Limitation of a Pathname to a Restricted Directory ('Path Traversal')\n\n**Mapping Guidance**:\n- Usage: Allowed\n- Rationale: This CWE entry is at the Base level of abstraction, which is a preferred level of abstraction for mapping to the root causes of vulnerabilities.\n\n**Relationships**:\n- CANFOLLOW -> CWE-73\n- PARENTOF -> CWE-36\n- PARENTOF -> CWE-23\n- CANFOLLOW -> CWE-20\n- CANFOLLOW -> CWE-172\n\n## CWE-619: Dangling Database Cursor ('Cursor Injection')\n**Abstraction Level**: base\n**Similarity Score**: 4.33\n**Source**: graph\n\n**Description**:\nCWE-619: Dangling Database Cursor ('Cursor Injection')\n\n**Mapping Guidance**:\n- Usage: Allowed\n- Rationale: This CWE entry is at the Base level of abstraction, which is a preferred level of abstraction for mapping to the root causes of vulnerabilities.\n\n**Relationships**:\n- CANFOLLOW -> CWE-404\n- CHILDOF -> CWE-402\n- CANPRECEDE -> CWE-619\n- PARENTOF -> CWE-619\n\n## CWE-98: Improper Control of Filename for Include/Require Statement in PHP Program ('PHP Remote File Inclusion')\n**Abstraction Level**: variant\n**Similarity Score**: 3.88\n**Source**: graph\n\n**Description**:\nCWE-98: Improper Control of Filename for Include/Require Statement in PHP Program ('PHP Remote File Inclusion')\n\n**Mapping Guidance**:\n- Usage: Allowed\n- Rationale: This CWE entry is at the Variant level of abstraction, which is a preferred level of abstraction for mapping to the root causes of vulnerabilities.\n\n**Relationships**:\n- CANFOLLOW -> CWE-73\n- CANFOLLOW -> CWE-473\n- CANFOLLOW -> CWE-456\n- CANFOLLOW -> CWE-425\n- CANFOLLOW -> CWE-184\n\n## CWE-351: Insufficient Type Distinction\n**Abstraction Level**: base\n**Similarity Score**: 3.64\n**Source**: graph\n\n**Description**:\nCWE-351: Insufficient Type Distinction\n\n**Mapping Guidance**:\n- Usage: Allowed\n- Rationale: This CWE entry is at the Base level of abstraction, which is a preferred level of abstraction for mapping to the root causes of vulnerabilities.\n\n**Relationships**:\n- PEEROF -> CWE-436\n- CHILDOF -> CWE-345\n- PEEROF -> CWE-351\n- PARENTOF -> CWE-351\n\n## CWE-430: Deployment of Wrong Handler\n**Abstraction Level**: base\n**Similarity Score**: 3.64\n**Source**: graph\n\n**Description**:\nCWE-430: Deployment of Wrong Handler\n\n**Mapping Guidance**:\n- Usage: Allowed\n- Rationale: This CWE entry is at the Base level of abstraction, which is a preferred level of abstraction for mapping to the root causes of vulnerabilities.\n\n**Relationships**:\n- PEEROF -> CWE-434\n- CANPRECEDE -> CWE-433\n- CHILDOF -> CWE-691\n- PARENTOF -> CWE-430\n- PEEROF -> CWE-430\n\n## CWE-266: Incorrect Privilege Assignment\n**Abstraction Level**: base\n**Similarity Score**: 3.64\n**Source**: graph\n\n**Description**:\nCWE-266: Incorrect Privilege Assignment\n\n**Mapping Guidance**:\n- Usage: Allowed\n- Rationale: This CWE entry is at the Base level of abstraction, which is a preferred level of abstraction for mapping to the root causes of vulnerabilities.\n\n**Relationships**:\n- PARENTOF -> CWE-9\n- PARENTOF -> CWE-556\n- PARENTOF -> CWE-520\n- PARENTOF -> CWE-1022\n-\n\n\n## CWE Relationship Analysis\n\nCurrent CWEs represent these abstraction levels: .\n\n\n### Vulnerability Chain Analysis\n\n**Chain starting from CWE-436:**\n- 436 (Interpretation Conflict) - ROOT\n\n\n**Chain starting from CWE-183:**\n- 183 (Permissive List of Allowed Inputs) - ROOT\n\n\n\n### CWE Relationship Diagram\n\n```mermaid\ngraph TD\n    classDef primary fill:#f96,stroke:#333,stroke-width:2px\n    classDef secondary fill:#69f,stroke:#333\n    classDef tertiary fill:#9e9,stroke:#333\n```",
  "criticism": "",
  "resolution": "",
  "relevant_cwes": [
    {
      "metadata": {
        "doc_id": "79",
        "name": "Improper Neutralization of Input During Web Page Generation ('Cross-site Scripting')",
        "source": "sparse"
      },
      "similarity": 396.5194645787765
    },
    {
      "metadata": {
        "doc_id": "89",
        "name": "Improper Neutralization of Special Elements used in an SQL Command ('SQL Injection')",
        "source": "sparse"
      },
      "similarity": 387.57436786258995
    },
    {
      "metadata": {
        "doc_id": "306",
        "name": "Missing Authentication for Critical Function",
        "source": "sparse"
      },
      "similarity": 359.32954587856193
    },
    {
      "metadata": {
        "doc_id": "287",
        "name": "Improper Authentication",
        "source": "sparse"
      },
      "similarity": 357.9583583187289
    },
    {
      "metadata": {
        "doc_id": "285",
        "name": "Improper Authorization",
        "source": "sparse"
      },
      "similarity": 353.8332402140188
    },
    {
      "metadata": {
        "doc_id": "404",
        "name": "Improper Resource Shutdown or Release",
        "source": "sparse"
      },
      "similarity": 348.3554140973186
    },
    {
      "metadata": {
        "doc_id": "266",
        "name": "Incorrect Privilege Assignment",
        "source": "sparse"
      },
      "similarity": 345.5793655088568
    },
    {
      "metadata": {
        "doc_id": "99",
        "name": "Improper Control of Resource Identifiers ('Resource Injection')",
        "source": "sparse"
      },
      "similarity": 344.0171092441979
    },
    {
      "metadata": {
        "doc_id": "434",
        "name": "Unrestricted Upload of File with Dangerous Type",
        "type": "Base",
        "original_content": "The product allows the upload or transfer of dangerous file types that are automatically processed within its environment.",
        "keyphrase_source": "weakness:improper access controls",
        "source": "dense",
        "mapping_notes": {
          "usage": "Allowed",
          "rationale": "This CWE entry is at the Base level of abstraction, which is a preferred level of abstraction for mapping to the root causes of vulnerabilities.",
          "comments": "Carefully read both the name and description to ensure that this mapping is an appropriate fit. Do not try to 'force' a mapping to a lower-level Base/Variant simply to comply with this preferred level of abstraction.",
          "reasons": [
            "Acceptable-Use"
          ]
        },
        "score_info": {
          "retrievers": [
            "dense",
            "graph"
          ],
          "retriever_count": 2,
          "normalized_scores": {
            "dense": 0.6073964881138383,
            "graph": 2.84963866739338
          }
        }
      },
      "similarity": 0.6073964881138383
    },
    {
      "doc_id": "73",
      "text": "The product allows user input to control or influence paths or file names that are used in filesystem operations.",
      "score": 0.6257112425121077,
      "metadata": {
        "doc_id": "73",
        "name": "External Control of File Name or Path",
        "type": "Base",
        "extended_description": "\n\nThis could allow an attacker to access or modify system files or other files that are critical to the application.\n\n\nPath manipulation errors occur when the following two conditions are met:\n\n```\n\t\t1. An attacker can specify a path used in an operation on the filesystem.\n\t\t2. By specifying the resource, the attacker gains a capability that would not otherwise be permitted.\n```\nFor example, the program may give the attacker the ability to overwrite the specified file or run with a configuration controlled by the attacker.",
        "alternate_terms": [],
        "original_content": "The product allows user input to control or influence paths or file names that are used in filesystem operations.",
        "relationships": [
          {
            "source_id": "73",
            "target_id": "114",
            "label": "PARENTOF",
            "properties": {
              "ordinal": "Primary",
              "view_id": "1000"
            }
          },
          {
            "source_id": "73",
            "target_id": "59",
            "label": "CANPRECEDE",
            "properties": {
              "view_id": "1000"
            }
          },
          {
            "source_id": "73",
            "target_id": "434",
            "label": "CANPRECEDE",
            "properties": {
              "view_id": "1000"
            }
          },
          {
            "source_id": "73",
            "target_id": "98",
            "label": "CANPRECEDE",
            "properties": {
              "view_id": "1000"
            }
          },
          {
            "source_id": "73",
            "target_id": "41",
            "label": "CANPRECEDE",
            "properties": {
              "view_id": "1000"
            }
          },
          {
            "source_id": "73",
            "target_id": "22",
            "label": "CANPRECEDE",
            "properties": {
              "view_id": "1000"
            }
          },
          {
            "source_id": "73",
            "target_id": "20",
            "label": "CHILDOF",
            "properties": {
              "ordinal": "Primary",
              "view_id": "700"
            }
          },
          {
            "source_id": "73",
            "target_id": "610",
            "label": "CHILDOF",
            "properties": {
              "view_id": "1000"
            }
          },
          {
            "source_id": "73",
            "target_id": "642",
            "label": "CHILDOF",
            "properties": {
              "ordinal": "Primary",
              "view_id": "1000"
            }
          },
          {
            "source_id": "99",
            "target_id": "73",
            "label": "CANALSOBE",
            "properties": {
              "view_id": "1000"
            }
          },
          {
            "source_id": "98",
            "target_id": "73",
            "label": "CANFOLLOW",
            "properties": {
              "view_id": "1000"
            }
          },
          {
            "source_id": "642",
            "target_id": "73",
            "label": "PARENTOF",
            "properties": {
              "ordinal": "Primary",
              "view_id": "1000"
            }
          },
          {
            "source_id": "610",
            "target_id": "73",
            "label": "PARENTOF",
            "properties": {
              "view_id": "1000"
            }
          },
          {
            "source_id": "59",
            "target_id": "73",
            "label": "CANFOLLOW",
            "properties": {
              "view_id": "1000"
            }
          },
          {
            "source_id": "434",
            "target_id": "73",
            "label": "CANFOLLOW",
            "properties": {
              "view_id": "1000"
            }
          },
          {
            "source_id": "41",
            "target_id": "73",
            "label": "CANFOLLOW",
            "properties": {
              "view_id": "1000"
            }
          },
          {
            "source_id": "22",
            "target_id": "73",
            "label": "CANFOLLOW",
            "properties": {
              "view_id": "1000"
            }
          },
          {
            "source_id": "20",
            "target_id": "73",
            "label": "PARENTOF",
            "properties": {
              "ordinal": "Primary",
              "view_id": "700"
            }
          },
          {
            "source_id": "114",
            "target_id": "73",
            "label": "CHILDOF",
            "properties": {
              "ordinal": "Primary",
              "view_id": "1000"
            }
          }
        ],
        "source": "graph",
        "sources": [
          "vector",
          "graph"
        ],
        "vector_score": 0.6257112425121077,
        "graph_score": 4.329000000000001,
        "score_components": {
          "relationship_chain": 1.0,
          "explicit_mention": 1.0,
          "abstraction_path": 0.9,
          "sequence_path": 1.0
        },
        "abstraction_factor": 1.3,
        "graph_path_info": {
          "path_types": [
            "relationship_chain",
            "vulnerability_sequence_forward",
            "vulnerability_sequence_backward"
          ],
          "best_paths": {
            "relationship_chain": {
              "path": [
                [
                  "434",
                  "73",
                  "CANFOLLOW"
                ]
              ],
              "score": 1.0,
              "type": "relationship_chain",
              "source": "434"
            },
            "vulnerability_sequence_forward": {
              "path": [
                [
                  "434",
                  "73",
                  "CANFOLLOW"
                ]
              ],
              "score": 0.9,
              "type": "vulnerability_sequence_forward",
              "source": "434"
            },
            "vulnerability_sequence_backward": {
              "path": [
                [
                  "73",
                  "434",
                  "CANPRECEDE"
                ]
              ],
              "score": 1.0,
              "type": "vulnerability_sequence_backward",
              "source": "434"
            }
          }
        },
        "is_explicit": true,
        "abstraction_level": "base",
        "position": "before",
        "mapping_notes": {
          "usage": "Allowed",
          "rationale": "This CWE entry is at the Base level of abstraction, which is a preferred level of abstraction for mapping to the root causes of vulnerabilities.",
          "comments": "Carefully read both the name and description to ensure that this mapping is an appropriate fit. Do not try to 'force' a mapping to a lower-level Base/Variant simply to comply with this preferred level of abstraction.",
          "reasons": [
            "Acceptable-Use"
          ]
        },
        "score_info": {
          "retrievers": [
            "dense",
            "graph"
          ],
          "retriever_count": 2,
          "normalized_scores": {
            "dense": 0.595241144064419,
            "graph": 2.8476844970048436
          }
        }
      },
      "similarity": 2.8476844970048436
    }
  ],
  "identified_cwes": {
    "analyzer": [
      "CWE-436",
      "CWE-183",
      "CWE-172",
      "CWE-285",
      "CWE-351",
      "CWE-98",
      "CWE-1022",
      "CWE-520",
      "CWE-22",
      "CWE-556",
      "CWE-345",
      "CWE-942",
      "CWE-266",
      "CWE-552",
      "CWE-494",
      "CWE-41",
      "CWE-59",
      "CWE-184",
      "CWE-456",
      "CWE-84",
      "CWE-9",
      "CWE-83",
      "CWE-87",
      "CWE-668",
      "CWE-73",
      "CWE-669",
      "CWE-116",
      "CWE-430",
      "CWE-23",
      "CWE-473",
      "CWE-862",
      "CWE-619",
      "CWE-691",
      "CWE-402",
      "CWE-610",
      "CWE-404",
      "CWE-79",
      "CWE-863",
      "CWE-433",
      "CWE-99",
      "CWE-85",
      "CWE-434",
      "CWE-86",
      "CWE-20",
      "CWE-36",
      "CWE-425",
      "CWE-697",
      "CWE-74"
    ],
    "critic_additional": []
  }
}