{
  "cve_id": "CVE-2025-5390",
  "description": "A vulnerability, which was classified as critical, was found in JeeWMS up to 20250504. This affects the function filedeal of the file /systemController/filedeal.do of the component File Handler. The manipulation leads to **improper access controls**. It is possible to initiate the attack remotely. This product does not use versioning. This is why information about affected and unaffected releases are unavailable.",
  "key_phrases": {
    "rootcause": "improper access controls",
    "weakness": "",
    "impact": "",
    "vector": "",
    "attacker": "",
    "product": "JeeWMS",
    "version": "up to 20250504",
    "component": "/systemController/filedeal.do"
  },
  "reference_content": "## Analysis of CVE-2025-5390 Content (gitee.com_4fcc10a4_20250624_164607.html)\n\nThis content **IS RELATED** to a set of vulnerabilities, though it doesn't directly reference CVE-2025-5390. It details multiple vulnerabilities found in the JeeWMS application hosted on Gitee. The content provides more detail than a typical CVE description would.\n\nHere's a breakdown of the extracted information:\n\n**Root cause of vulnerability:**\n\nThe root causes vary depending on the vulnerability, including:\n\n*   **SQL Injection:** Improper input validation allowing malicious SQL code execution.\n*   **Path Traversal:** Insufficient sanitization of file paths, enabling access to arbitrary files.\n*   **Arbitrary File Read:** Lack of proper access controls allowing reading of any file.\n*   **Arbitrary File Write:** Lack of proper access controls allowing writing to any file.\n*   **Remote Code Execution (RCE):** Ability to write controllable JSP files to arbitrary locations, leading to code execution.\n\n**Weaknesses/vulnerabilities present:**\n\n*   SQL Injection (in `CgAutoListController.do?datagrid` and `cgformTransController.do?transEditor` and `generateController.do?dogenerate`)\n*   Path Traversal (in `cgformTemplateController.do?doAdd`)\n*   Arbitrary File Read (in `cgformTemplateController.do?showPic`)\n*   Arbitrary File Write (in `generateController.do?dogenerate`, `generateController.do?dogenerateOne2Many`, and `systemController/filedeal.do`)\n*   Remote Code Execution (RCE) (in `generateController.do?dogenerate` and `generateController.do?dogenerateOne2Many`)\n\n**Impact of exploitation:**\n\n*   **SQL Injection:** Data breach, data manipulation, potential system compromise.\n*   **Path Traversal:** Unauthorized access to sensitive files, potential system compromise.\n*   **Arbitrary File Read:** Exposure of sensitive information.\n*   **Arbitrary File Write:**  Overwriting critical system files, potential system compromise.\n*   **Remote Code Execution (RCE):** Complete system compromise, allowing attackers to execute arbitrary code on the server.\n\n**Attack vectors:**\n\n*   HTTP requests to specific controller methods with crafted parameters.  The specific request paths are provided for each vulnerability.\n\n**Required attacker capabilities/position:**\n\n*   Unauthenticated attacker (likely, as no authentication is mentioned as a prerequisite for exploitation in the provided text).\n*   Ability to send HTTP requests to the JeeWMS application.\n*   Knowledge of the vulnerable request paths and parameters.\n\n**Mitigation or fix:**\n\nThe content does *not* provide specific mitigation or fix details. It states that the vulnerability details and PoCs have been sent to the vendor (huayi-tec.com) via email.",
  "similar_info": {
    "cwe_distribution": {},
    "cwe_consensus": "",
    "similarity_stats": {
      "thresholds": [],
      "total_samples_by_threshold": {},
      "top_cwes_by_threshold": {}
    }
  },
  "similarity_summary": {
    "consensus_cwe": "",
    "top_cwes": [],
    "confidence_levels": {},
    "total_samples": 0
  },
  "analysis": "# Summary\n| CWE ID | CWE Name | Confidence | CWE Abstraction Level | CWE Vulnerability Mapping Label | CWE-Vulnerability Mapping Notes |\n|---|---|---|---|---|---|\n| CWE-285 | Improper Authorization | 0.8 | Class | Primary | Allowed-with-Review |\n| CWE-269 | Improper Privilege Management | 0.6 | Class | Secondary | Discouraged |\n| CWE-306 | Missing Authentication for Critical Function | 0.4 | Secondary | Allowed |\n\n## Evidence and Confidence\n\n*   **Confidence Score:** 0.8\n*   **Evidence Strength:** MEDIUM\n\n## Relationship Analysis\nThe primary CWE selected is CWE-285, Improper Authorization. This is a class-level CWE that describes a situation where a product does not properly perform an authorization check. CWE-269, Improper Privilege Management, is a peer of CWE-285, and was considered because it is also related to access control issues, but it's more about the incorrect assignment or tracking of privileges. CWE-306, Missing Authentication for Critical Function, was also considered as authentication often precedes authorization, but the vulnerability description specifically mentions \"improper access controls,\" pointing more directly to authorization.\n\n```mermaid\ngraph TD\n    cwe285[\"CWE-285: Improper Authorization\"]\n    cwe269[\"CWE-269: Improper Privilege Management\"]\n    cwe306[\"CWE-306: Missing Authentication for Critical Function\"]\n    cwe284[\"CWE-284: Improper Access Control\"]\n    \n\n    cwe285 -->|CHILDOF| cwe284\n    cwe269 -->|CHILDOF| cwe284\n    cwe306 -->|CHILDOF| cwe287\n    cwe287[\"CWE-287: Improper Authentication\"] -->|CHILDOF| cwe284\n    \n\n    classDef primary fill:#f96,stroke:#333,stroke-width:2px\n    classDef secondary fill:#69f,stroke:#333\n    classDef tertiary fill:#9e9,stroke:#333\n    class cwe285 primary\n    class cwe269,cwe306 secondary\n```\n\n## Vulnerability Chain\nThe vulnerability chain starts with the **improper access controls** (CWE-285). This leads to unauthorized access to the `filedeal` function, potentially resulting in arbitrary file read/write or other unauthorized operations depending on the specifics of the file handling logic.\n  - Root Cause: **Improper Access Controls** (CWE-285)\n  - Impact: Unauthorized access to `filedeal` function, potentially leading to arbitrary file operations.\n\n## Summary of Analysis\nThe initial assessment strongly points towards CWE-285 due to the explicit mention of **improper access controls** in the vulnerability description. The CVE Reference Links Content Summary reinforces this by detailing Arbitrary File Read/Write vulnerabilities within the JeeWMS application due to \"lack of proper access controls.\"\n\nThe evidence supporting CWE-285 is quite strong given that the description highlights the access control issue. The retriever also lists CWE-285 and its related access control CWEs as potential candidates.\n\nThe graph relationships helped to clarify the distinction between authentication and authorization, guiding the selection towards the more specific authorization-related CWE.\n\nThe choice of CWE-285 is at the appropriate level of specificity as it directly addresses the core weakness of improper authorization, without delving into specific implementation details that are not provided in the description.\n\nRelevant CWE Information:\n\n# Enhanced Context (25 CWEs)\nThe following CWEs were identified as potentially relevant to this vulnerability:\n\n## CWE-73: External Control of File Name or Path\n**Abstraction Level**: Base\n**Similarity Score**: 0.81\n**Source**: dense\n\n**Description**:\nThe product allows user input to control or influence paths or file names that are used in filesystem operations.\n\n**Mapping Guidance**:\n- Usage: Allowed\n- Rationale: This CWE entry is at the Base level of abstraction, which is a preferred level of abstraction for mapping to the root causes of vulnerabilities.\n\n\n\n## CWE-23: Relative Path Traversal\n**Abstraction Level**: Base\n**Similarity Score**: 0.80\n**Source**: dense\n\n**Description**:\nThe product uses external input to construct a pathname that should be within a restricted directory, but it does not properly neutralize sequences such as \"..\" that can resolve to a location that is outside of that directory.\n\n**Mapping Guidance**:\n- Usage: Allowed\n- Rationale: This CWE entry is at the Base level of abstraction, which is a preferred level of abstraction for mapping to the root causes of vulnerabilities.\n\n\n\n## CWE-41: Improper Resolution of Path Equivalence\n**Abstraction Level**: Base\n**Similarity Score**: 0.80\n**Source**: dense\n\n**Description**:\nThe product is vulnerable to file system contents disclosure through path equivalence. Path equivalence involves the use of special characters in file and directory names. The associated manipulations are intended to generate multiple names for the same object.\n\n**Mapping Guidance**:\n- Usage: Allowed\n- Rationale: This CWE entry is at the Base level of abstraction, which is a preferred level of abstraction for mapping to the root causes of vulnerabilities.\n\n\n\n## CWE-59: Improper Link Resolution Before File Access ('Link Following')\n**Abstraction Level**: Base\n**Similarity Score**: 0.79\n**Source**: dense\n\n**Description**:\nThe product attempts to access a file based on the filename, but it does not properly prevent that filename from identifying a link or shortcut that resolves to an unintended resource.\n\n**Mapping Guidance**:\n- Usage: Allowed\n- Rationale: This CWE entry is at the Base level of abstraction, which is a preferred level of abstraction for mapping to the root causes of vulnerabilities.\n\n\n\n## CWE-668: Exposure of Resource to Wrong Sphere\n**Abstraction Level**: Class\n**Similarity Score**: 0.78\n**Source**: dense\n\n**Description**:\nThe product exposes a resource to the wrong control sphere, providing unintended actors with inappropriate access to the resource.\n\n**Mapping Guidance**:\n- Usage: Discouraged\n- Rationale: CWE-668 is high-level and is often misused as a catch-all when lower-level CWE IDs might be applicable. It is sometimes used for low-information vulnerability reports [REF-1287]. It is a level-1 Class (i.e., a child of a Pillar). It is not useful for trend analysis.\n\n\n\n## CWE-552: Files or Directories Accessible to External Parties\n**Abstraction Level**: Base\n**Similarity Score**: 0.78\n**Source**: dense\n\n**Description**:\nThe product makes files or directories accessible to unauthorized actors, even though they should not be.\n\n**Mapping Guidance**:\n- Usage: Allowed\n- Rationale: This CWE entry is at the Base level of abstraction, which is a preferred level of abstraction for mapping to the root causes of vulnerabilities.\n\n\n\n## CWE-36: Absolute Path Traversal\n**Abstraction Level**: Base\n**Similarity Score**: 0.77\n**Source**: dense\n\n**Description**:\nThe product uses external input to construct a pathname that should be within a restricted directory, but it does not properly neutralize absolute path sequences such as \"/abs/path\" that can resolve to a location that is outside of that directory.\n\n**Mapping Guidance**:\n- Usage: Allowed\n- Rationale: This CWE entry is at the Base level of abstraction, which is a preferred level of abstraction for mapping to the root causes of vulnerabilities.\n\n\n\n## CWE-74: Improper Neutralization of Special Elements in Output Used by a Downstream Component ('Injection')\n**Abstraction Level**: Class\n**Similarity Score**: 0.77\n**Source**: dense\n\n**Description**:\nThe product constructs all or part of a command, data structure, or record using externally-influenced input from an upstream component, but it does not neutralize or incorrectly neutralizes special elements that could modify how it is parsed or interpreted when it is sent to a downstream component.\n\n**Mapping Guidance**:\n- Usage: Discouraged\n- Rationale: CWE-74 is high-level and often misused when lower-level weaknesses are more appropriate.\n\n\n\n## CWE-184: Incomplete List of Disallowed Inputs\n**Abstraction Level**: Base\n**Similarity Score**: 0.77\n**Source**: dense\n\n**Description**:\nThe product implements a protection mechanism that relies on a list of inputs (or properties of inputs) that are not allowed by policy or otherwise require other action to neutralize before additional processing takes place, but the list is incomplete.\n\n**Mapping Guidance**:\n- Usage: Allowed\n- Rationale: This CWE entry is at the Base level of abstraction, which is a preferred level of abstraction for mapping to the root causes of vulnerabilities.\n\n\n\n## CWE-24: Path Traversal: '../filedir'\n**Abstraction Level**: Variant\n**Similarity Score**: 0.77\n**Source**: dense\n\n**Description**:\nThe product uses external input to construct a pathname that should be within a restricted directory, but it does not properly neutralize \"../\" sequences that can resolve to a location that is outside of that directory.\n\n**Mapping Guidance**:\n- Usage: Allowed\n- Rationale: This CWE entry is at the Variant level of abstraction, which is a preferred level of abstraction for mapping to the root causes of vulnerabilities.\n\n\n\n## CWE-22: Improper Limitation of a Pathname to a Restricted Directory ('Path Traversal')\n**Abstraction Level**: Base\n**Similarity Score**: 7608.08\n**Source**: sparse\n\n**Description**:\nThe product uses external input to construct a pathname that is intended to identify a file or directory that is located underneath a restricted parent directory, but the product does not properly neutralize special elements within the pathname that can cause the pathname to resolve to a location that is outside of the restricted directory.\n\n**Mapping Guidance**:\n- Usage: Allowed\n- Rationale: This CWE entry is at the Base level of abstraction, which is a preferred level of abstraction for mapping to the root causes of vulnerabilities.\n\n\n\n## CWE-79: Improper Neutralization of Input During Web Page Generation ('Cross-site Scripting')\n**Abstraction Level**: Base\n**Similarity Score**: 7469.93\n**Source**: sparse\n\n**Description**:\nThe product does not neutralize or incorrectly neutralizes user-controllable input before it is placed in output that is used as a web page that is served to other users.\n\n**Mapping Guidance**:\n- Usage: Allowed\n- Rationale: This CWE entry is at the Base level of abstraction, which is a preferred level of abstraction for mapping to the root causes of vulnerabilities.\n\n\n\n## CWE-23: Relative Path Traversal\n**Abstraction Level**: Base\n**Similarity Score**: 7262.40\n**Source**: sparse\n\n**Description**:\nThe product uses external input to construct a pathname that should be within a restricted directory, but it does not properly neutralize sequences such as \"..\" that can resolve to a location that is outside of that directory.\n\n**Mapping Guidance**:\n- Usage: Allowed\n- Rationale: This CWE entry is at the Base level of abstraction, which is a preferred level of abstraction for mapping to the root causes of vulnerabilities.\n\n\n\n## CWE-116: Improper Encoding or Escaping of Output\n**Abstraction Level**: Class\n**Similarity Score**: 7142.76\n**Source**: sparse\n\n**Description**:\nThe product prepares a structured message for communication with another component, but encoding or escaping of the data is either missing or done incorrectly. As a result, the intended structure of the message is not preserved.\n\n**Mapping Guidance**:\n- Usage: Allowed-with-Review\n- Rationale: This CWE entry is a Class and might have Base-level children that would be more appropriate\n\n\n\n## CWE-863: Incorrect Authorization\n**Abstraction Level**: Class\n**Similarity Score**: 7120.89\n**Source**: sparse\n\n**Description**:\nThe product performs an authorization check when an actor attempts to access a resource or perform an action, but it does not correctly perform the check.\n\n**Mapping Guidance**:\n- Usage: Allowed-with-Review\n- Rationale: This CWE entry is a Class and might have Base-level children that would be more appropriate\n\n\n\n## CWE-79: Improper Neutralization of Input During Web Page Generation ('Cross-site Scripting')\n**Abstraction Level**: base\n**Similarity Score**: 5.03\n**Source**: graph\n\n**Description**:\nCWE-79: Improper Neutralization of Input During Web Page Generation ('Cross-site Scripting')\n\n**Mapping Guidance**:\n- Usage: Allowed\n- Rationale: This CWE entry is at the Base level of abstraction, which is a preferred level of abstraction for mapping to the root causes of vulnerabilities.\n\n**Relationships**:\n- PARENTOF -> CWE-87\n- PARENTOF -> CWE-86\n- PARENTOF -> CWE-85\n- PARENTOF -> CWE-84\n- PARENTOF -> CWE-83\n\n\n\n## CWE-494: Download of Code Without Integrity Check\n**Abstraction Level**: base\n**Similarity Score**: 4.33\n**Source**: graph\n\n**Description**:\nCWE-494: Download of Code Without Integrity Check\n\n**Mapping Guidance**:\n- Usage: Allowed\n- Rationale: This CWE entry is at the Base level of abstraction, which is a preferred level of abstraction for mapping to the root causes of vulnerabilities.\n\n**Relationships**:\n- CANFOLLOW -> CWE-79\n- CHILDOF -> CWE-669\n- CHILDOF -> CWE-669\n- CHILDOF -> CWE-345\n- CANPRECEDE -> CWE-494\n\n\n\n## CWE-22: Improper Limitation of a Pathname to a Restricted Directory ('Path Traversal')\n**Abstraction Level**: base\n**Similarity Score**: 4.33\n**Source**: graph\n\n**Description**:\nCWE-22: Improper Limitation of a Pathname to a Restricted Directory ('Path Traversal')\n\n**Mapping Guidance**:\n- Usage: Allowed\n- Rationale: This CWE entry is at the Base level of abstraction, which is a preferred level of abstraction for mapping to the root causes of vulnerabilities.\n\n**Relationships**:\n- CANFOLLOW -> CWE-73\n- PARENTOF -> CWE-36\n- PARENTOF -> CWE-23\n- CANFOLLOW -> CWE-20\n- CANFOLLOW -> CWE-172\n\n\n\n## CWE-434: Unrestricted Upload of File with Dangerous Type\n**Abstraction Level**: base\n**Similarity Score**: 4.33\n**Source**: graph\n\n**Description**:\nCWE-434: Unrestricted Upload of File with Dangerous Type\n\n**Mapping Guidance**:\n- Usage: Allowed\n- Rationale: This CWE entry is at the Base level of abstraction, which is a preferred level of abstraction for mapping to the root causes of vulnerabilities.\n\n**Relationships**:\n- CANFOLLOW -> CWE-73\n- CANFOLLOW -> CWE-184\n- CANFOLLOW -> CWE-183\n- PEEROF -> CWE-430\n- PEEROF -> CWE-436\n\n\n\n## CWE-98: Improper Control of Filename for Include/Require Statement in PHP Program ('PHP Remote File Inclusion')\n**Abstraction Level**: variant\n**Similarity Score**: 3.88\n**Source**: graph\n\n**Description**:\nCWE-98: Improper Control of Filename for Include/Require Statement in PHP Program ('PHP Remote File Inclusion')\n\n**Mapping Guidance**:\n- Usage: Allowed\n- Rationale: This CWE entry is at the Variant level of abstraction, which is a preferred level of abstraction for mapping to the root causes of vulnerabilities.\n\n**Relationships**:\n- CANFOLLOW -> CWE-73\n- CANFOLLOW -> CWE-473\n- CANFOLLOW -> CWE-456\n- CANFOLLOW -> CWE-425\n- CANFOLLOW -> CWE-184\n\n\n\n## CWE-352: Cross-Site Request Forgery (CSRF)\n**Abstraction Level**: compound\n**Similarity Score**: 3.46\n**Source**: graph\n\n**Description**:\nCWE-352: Cross-Site Request Forgery (CSRF)\n\n**Mapping Guidance**:\n- Usage: Allowed\n- Rationale: This is a well-known Composite of multiple weaknesses that must all occur simultaneously, although it is attack-oriented in nature.\n\n**Relationships**:\n- CANFOLLOW -> CWE-1275\n- REQUIRES -> CWE-613\n- REQUIRES -> CWE-642\n- REQUIRES -> CWE-441\n- REQUIRES -> CWE-346\n\n\n\n## CWE-843: Access of Resource Using Incompatible Type ('Type Confusion')\n**Abstraction Level**: base\n**Similarity Score**: 3.44\n**Source**: graph\n\n**Description**:\nCWE-843: Access of Resource Using Incompatible Type ('Type Confusion')\n\n**Mapping Guidance**:\n- Usage: Allowed\n- Rationale: This CWE entry is at the Base level of abstraction, which is a preferred level of abstraction for mapping to the root causes of vulnerabilities.\n\n**Relationships**:\n- CANPRECEDE -> CWE-119\n- CHILDOF -> CWE-704\n- CHILDOF -> CWE-704\n- PARENTOF -> CWE-843\n- PEEROF -> CWE-843\n\n\n\n## CWE-89: Improper Neutralization of Special Elements used in an SQL Command ('SQL Injection')\n**Abstraction Level**: base\n**Similarity Score**: 3.30\n**Source**: graph\n\n**Description**:\nCWE-89: Improper Neutralization of Special Elements used in an SQL Command ('SQL Injection')\n\n**Mapping Guidance**:\n- Usage: Allowed\n- Rationale: This CWE entry is at the Base level of abstraction, which is a preferred level of abstraction for mapping to the root causes of vulnerabilities.\n\n**Relationships**:\n- PARENTOF -> CWE-564\n- CANFOLLOW -> CWE-456\n- CHILDOF -> CWE-74\n- CHILDOF -> CWE-943\n- PARENTOF -> CWE-89\n\n\n\n## CWE-73: External Control of File Name or Path\n**Abstraction Level**: Base\n**Similarity Score**: 3.22\n**Source**: graph\n\n**Description**:\nThe product allows user input to control or influence paths or file names that are used in filesystem operations.\n\n**Mapping Guidance**:\n- Usage: Allowed\n- Rationale: This CWE entry is at the Base level of abstraction, which is a preferred level of abstraction for mapping to the root causes of vulnerabilities.\n\n**Relationships**:\n- PARENTOF -> CWE-114\n- CANPRECEDE -> CWE-5",
  "analysis_with_relationships": "# Summary\n| CWE ID | CWE Name | Confidence | CWE Abstraction Level | CWE Vulnerability Mapping Label | CWE-Vulnerability Mapping Notes |\n|---|---|---|---|---|---|\n| CWE-285 | Improper Authorization | 0.8 | Class | Primary | Allowed-with-Review |\n| CWE-269 | Improper Privilege Management | 0.6 | Class | Secondary | Discouraged |\n| CWE-306 | Missing Authentication for Critical Function | 0.4 | Secondary | Allowed |\n\n## Evidence and Confidence\n\n*   **Confidence Score:** 0.8\n*   **Evidence Strength:** MEDIUM\n\n## Relationship Analysis\nThe primary CWE selected is CWE-285, Improper Authorization. This is a class-level CWE that describes a situation where a product does not properly perform an authorization check. CWE-269, Improper Privilege Management, is a peer of CWE-285, and was considered because it is also related to access control issues, but it's more about the incorrect assignment or tracking of privileges. CWE-306, Missing Authentication for Critical Function, was also considered as authentication often precedes authorization, but the vulnerability description specifically mentions \"improper access controls,\" pointing more directly to authorization.\n\n```mermaid\ngraph TD\n    cwe285[\"CWE-285: Improper Authorization\"]\n    cwe269[\"CWE-269: Improper Privilege Management\"]\n    cwe306[\"CWE-306: Missing Authentication for Critical Function\"]\n    cwe284[\"CWE-284: Improper Access Control\"]\n    \n\n    cwe285 -->|CHILDOF| cwe284\n    cwe269 -->|CHILDOF| cwe284\n    cwe306 -->|CHILDOF| cwe287\n    cwe287[\"CWE-287: Improper Authentication\"] -->|CHILDOF| cwe284\n    \n\n    classDef primary fill:#f96,stroke:#333,stroke-width:2px\n    classDef secondary fill:#69f,stroke:#333\n    classDef tertiary fill:#9e9,stroke:#333\n    class cwe285 primary\n    class cwe269,cwe306 secondary\n```\n\n## Vulnerability Chain\nThe vulnerability chain starts with the **improper access controls** (CWE-285). This leads to unauthorized access to the `filedeal` function, potentially resulting in arbitrary file read/write or other unauthorized operations depending on the specifics of the file handling logic.\n  - Root Cause: **Improper Access Controls** (CWE-285)\n  - Impact: Unauthorized access to `filedeal` function, potentially leading to arbitrary file operations.\n\n## Summary of Analysis\nThe initial assessment strongly points towards CWE-285 due to the explicit mention of **improper access controls** in the vulnerability description. The CVE Reference Links Content Summary reinforces this by detailing Arbitrary File Read/Write vulnerabilities within the JeeWMS application due to \"lack of proper access controls.\"\n\nThe evidence supporting CWE-285 is quite strong given that the description highlights the access control issue. The retriever also lists CWE-285 and its related access control CWEs as potential candidates.\n\nThe graph relationships helped to clarify the distinction between authentication and authorization, guiding the selection towards the more specific authorization-related CWE.\n\nThe choice of CWE-285 is at the appropriate level of specificity as it directly addresses the core weakness of improper authorization, without delving into specific implementation details that are not provided in the description.\n\nRelevant CWE Information:\n\n# Enhanced Context (25 CWEs)\nThe following CWEs were identified as potentially relevant to this vulnerability:\n\n## CWE-73: External Control of File Name or Path\n**Abstraction Level**: Base\n**Similarity Score**: 0.81\n**Source**: dense\n\n**Description**:\nThe product allows user input to control or influence paths or file names that are used in filesystem operations.\n\n**Mapping Guidance**:\n- Usage: Allowed\n- Rationale: This CWE entry is at the Base level of abstraction, which is a preferred level of abstraction for mapping to the root causes of vulnerabilities.\n\n\n\n## CWE-23: Relative Path Traversal\n**Abstraction Level**: Base\n**Similarity Score**: 0.80\n**Source**: dense\n\n**Description**:\nThe product uses external input to construct a pathname that should be within a restricted directory, but it does not properly neutralize sequences such as \"..\" that can resolve to a location that is outside of that directory.\n\n**Mapping Guidance**:\n- Usage: Allowed\n- Rationale: This CWE entry is at the Base level of abstraction, which is a preferred level of abstraction for mapping to the root causes of vulnerabilities.\n\n\n\n## CWE-41: Improper Resolution of Path Equivalence\n**Abstraction Level**: Base\n**Similarity Score**: 0.80\n**Source**: dense\n\n**Description**:\nThe product is vulnerable to file system contents disclosure through path equivalence. Path equivalence involves the use of special characters in file and directory names. The associated manipulations are intended to generate multiple names for the same object.\n\n**Mapping Guidance**:\n- Usage: Allowed\n- Rationale: This CWE entry is at the Base level of abstraction, which is a preferred level of abstraction for mapping to the root causes of vulnerabilities.\n\n\n\n## CWE-59: Improper Link Resolution Before File Access ('Link Following')\n**Abstraction Level**: Base\n**Similarity Score**: 0.79\n**Source**: dense\n\n**Description**:\nThe product attempts to access a file based on the filename, but it does not properly prevent that filename from identifying a link or shortcut that resolves to an unintended resource.\n\n**Mapping Guidance**:\n- Usage: Allowed\n- Rationale: This CWE entry is at the Base level of abstraction, which is a preferred level of abstraction for mapping to the root causes of vulnerabilities.\n\n\n\n## CWE-668: Exposure of Resource to Wrong Sphere\n**Abstraction Level**: Class\n**Similarity Score**: 0.78\n**Source**: dense\n\n**Description**:\nThe product exposes a resource to the wrong control sphere, providing unintended actors with inappropriate access to the resource.\n\n**Mapping Guidance**:\n- Usage: Discouraged\n- Rationale: CWE-668 is high-level and is often misused as a catch-all when lower-level CWE IDs might be applicable. It is sometimes used for low-information vulnerability reports [REF-1287]. It is a level-1 Class (i.e., a child of a Pillar). It is not useful for trend analysis.\n\n\n\n## CWE-552: Files or Directories Accessible to External Parties\n**Abstraction Level**: Base\n**Similarity Score**: 0.78\n**Source**: dense\n\n**Description**:\nThe product makes files or directories accessible to unauthorized actors, even though they should not be.\n\n**Mapping Guidance**:\n- Usage: Allowed\n- Rationale: This CWE entry is at the Base level of abstraction, which is a preferred level of abstraction for mapping to the root causes of vulnerabilities.\n\n\n\n## CWE-36: Absolute Path Traversal\n**Abstraction Level**: Base\n**Similarity Score**: 0.77\n**Source**: dense\n\n**Description**:\nThe product uses external input to construct a pathname that should be within a restricted directory, but it does not properly neutralize absolute path sequences such as \"/abs/path\" that can resolve to a location that is outside of that directory.\n\n**Mapping Guidance**:\n- Usage: Allowed\n- Rationale: This CWE entry is at the Base level of abstraction, which is a preferred level of abstraction for mapping to the root causes of vulnerabilities.\n\n\n\n## CWE-74: Improper Neutralization of Special Elements in Output Used by a Downstream Component ('Injection')\n**Abstraction Level**: Class\n**Similarity Score**: 0.77\n**Source**: dense\n\n**Description**:\nThe product constructs all or part of a command, data structure, or record using externally-influenced input from an upstream component, but it does not neutralize or incorrectly neutralizes special elements that could modify how it is parsed or interpreted when it is sent to a downstream component.\n\n**Mapping Guidance**:\n- Usage: Discouraged\n- Rationale: CWE-74 is high-level and often misused when lower-level weaknesses are more appropriate.\n\n\n\n## CWE-184: Incomplete List of Disallowed Inputs\n**Abstraction Level**: Base\n**Similarity Score**: 0.77\n**Source**: dense\n\n**Description**:\nThe product implements a protection mechanism that relies on a list of inputs (or properties of inputs) that are not allowed by policy or otherwise require other action to neutralize before additional processing takes place, but the list is incomplete.\n\n**Mapping Guidance**:\n- Usage: Allowed\n- Rationale: This CWE entry is at the Base level of abstraction, which is a preferred level of abstraction for mapping to the root causes of vulnerabilities.\n\n\n\n## CWE-24: Path Traversal: '../filedir'\n**Abstraction Level**: Variant\n**Similarity Score**: 0.77\n**Source**: dense\n\n**Description**:\nThe product uses external input to construct a pathname that should be within a restricted directory, but it does not properly neutralize \"../\" sequences that can resolve to a location that is outside of that directory.\n\n**Mapping Guidance**:\n- Usage: Allowed\n- Rationale: This CWE entry is at the Variant level of abstraction, which is a preferred level of abstraction for mapping to the root causes of vulnerabilities.\n\n\n\n## CWE-22: Improper Limitation of a Pathname to a Restricted Directory ('Path Traversal')\n**Abstraction Level**: Base\n**Similarity Score**: 7608.08\n**Source**: sparse\n\n**Description**:\nThe product uses external input to construct a pathname that is intended to identify a file or directory that is located underneath a restricted parent directory, but the product does not properly neutralize special elements within the pathname that can cause the pathname to resolve to a location that is outside of the restricted directory.\n\n**Mapping Guidance**:\n- Usage: Allowed\n- Rationale: This CWE entry is at the Base level of abstraction, which is a preferred level of abstraction for mapping to the root causes of vulnerabilities.\n\n\n\n## CWE-79: Improper Neutralization of Input During Web Page Generation ('Cross-site Scripting')\n**Abstraction Level**: Base\n**Similarity Score**: 7469.93\n**Source**: sparse\n\n**Description**:\nThe product does not neutralize or incorrectly neutralizes user-controllable input before it is placed in output that is used as a web page that is served to other users.\n\n**Mapping Guidance**:\n- Usage: Allowed\n- Rationale: This CWE entry is at the Base level of abstraction, which is a preferred level of abstraction for mapping to the root causes of vulnerabilities.\n\n\n\n## CWE-23: Relative Path Traversal\n**Abstraction Level**: Base\n**Similarity Score**: 7262.40\n**Source**: sparse\n\n**Description**:\nThe product uses external input to construct a pathname that should be within a restricted directory, but it does not properly neutralize sequences such as \"..\" that can resolve to a location that is outside of that directory.\n\n**Mapping Guidance**:\n- Usage: Allowed\n- Rationale: This CWE entry is at the Base level of abstraction, which is a preferred level of abstraction for mapping to the root causes of vulnerabilities.\n\n\n\n## CWE-116: Improper Encoding or Escaping of Output\n**Abstraction Level**: Class\n**Similarity Score**: 7142.76\n**Source**: sparse\n\n**Description**:\nThe product prepares a structured message for communication with another component, but encoding or escaping of the data is either missing or done incorrectly. As a result, the intended structure of the message is not preserved.\n\n**Mapping Guidance**:\n- Usage: Allowed-with-Review\n- Rationale: This CWE entry is a Class and might have Base-level children that would be more appropriate\n\n\n\n## CWE-863: Incorrect Authorization\n**Abstraction Level**: Class\n**Similarity Score**: 7120.89\n**Source**: sparse\n\n**Description**:\nThe product performs an authorization check when an actor attempts to access a resource or perform an action, but it does not correctly perform the check.\n\n**Mapping Guidance**:\n- Usage: Allowed-with-Review\n- Rationale: This CWE entry is a Class and might have Base-level children that would be more appropriate\n\n\n\n## CWE-79: Improper Neutralization of Input During Web Page Generation ('Cross-site Scripting')\n**Abstraction Level**: base\n**Similarity Score**: 5.03\n**Source**: graph\n\n**Description**:\nCWE-79: Improper Neutralization of Input During Web Page Generation ('Cross-site Scripting')\n\n**Mapping Guidance**:\n- Usage: Allowed\n- Rationale: This CWE entry is at the Base level of abstraction, which is a preferred level of abstraction for mapping to the root causes of vulnerabilities.\n\n**Relationships**:\n- PARENTOF -> CWE-87\n- PARENTOF -> CWE-86\n- PARENTOF -> CWE-85\n- PARENTOF -> CWE-84\n- PARENTOF -> CWE-83\n\n\n\n## CWE-494: Download of Code Without Integrity Check\n**Abstraction Level**: base\n**Similarity Score**: 4.33\n**Source**: graph\n\n**Description**:\nCWE-494: Download of Code Without Integrity Check\n\n**Mapping Guidance**:\n- Usage: Allowed\n- Rationale: This CWE entry is at the Base level of abstraction, which is a preferred level of abstraction for mapping to the root causes of vulnerabilities.\n\n**Relationships**:\n- CANFOLLOW -> CWE-79\n- CHILDOF -> CWE-669\n- CHILDOF -> CWE-669\n- CHILDOF -> CWE-345\n- CANPRECEDE -> CWE-494\n\n\n\n## CWE-22: Improper Limitation of a Pathname to a Restricted Directory ('Path Traversal')\n**Abstraction Level**: base\n**Similarity Score**: 4.33\n**Source**: graph\n\n**Description**:\nCWE-22: Improper Limitation of a Pathname to a Restricted Directory ('Path Traversal')\n\n**Mapping Guidance**:\n- Usage: Allowed\n- Rationale: This CWE entry is at the Base level of abstraction, which is a preferred level of abstraction for mapping to the root causes of vulnerabilities.\n\n**Relationships**:\n- CANFOLLOW -> CWE-73\n- PARENTOF -> CWE-36\n- PARENTOF -> CWE-23\n- CANFOLLOW -> CWE-20\n- CANFOLLOW -> CWE-172\n\n\n\n## CWE-434: Unrestricted Upload of File with Dangerous Type\n**Abstraction Level**: base\n**Similarity Score**: 4.33\n**Source**: graph\n\n**Description**:\nCWE-434: Unrestricted Upload of File with Dangerous Type\n\n**Mapping Guidance**:\n- Usage: Allowed\n- Rationale: This CWE entry is at the Base level of abstraction, which is a preferred level of abstraction for mapping to the root causes of vulnerabilities.\n\n**Relationships**:\n- CANFOLLOW -> CWE-73\n- CANFOLLOW -> CWE-184\n- CANFOLLOW -> CWE-183\n- PEEROF -> CWE-430\n- PEEROF -> CWE-436\n\n\n\n## CWE-98: Improper Control of Filename for Include/Require Statement in PHP Program ('PHP Remote File Inclusion')\n**Abstraction Level**: variant\n**Similarity Score**: 3.88\n**Source**: graph\n\n**Description**:\nCWE-98: Improper Control of Filename for Include/Require Statement in PHP Program ('PHP Remote File Inclusion')\n\n**Mapping Guidance**:\n- Usage: Allowed\n- Rationale: This CWE entry is at the Variant level of abstraction, which is a preferred level of abstraction for mapping to the root causes of vulnerabilities.\n\n**Relationships**:\n- CANFOLLOW -> CWE-73\n- CANFOLLOW -> CWE-473\n- CANFOLLOW -> CWE-456\n- CANFOLLOW -> CWE-425\n- CANFOLLOW -> CWE-184\n\n\n\n## CWE-352: Cross-Site Request Forgery (CSRF)\n**Abstraction Level**: compound\n**Similarity Score**: 3.46\n**Source**: graph\n\n**Description**:\nCWE-352: Cross-Site Request Forgery (CSRF)\n\n**Mapping Guidance**:\n- Usage: Allowed\n- Rationale: This is a well-known Composite of multiple weaknesses that must all occur simultaneously, although it is attack-oriented in nature.\n\n**Relationships**:\n- CANFOLLOW -> CWE-1275\n- REQUIRES -> CWE-613\n- REQUIRES -> CWE-642\n- REQUIRES -> CWE-441\n- REQUIRES -> CWE-346\n\n\n\n## CWE-843: Access of Resource Using Incompatible Type ('Type Confusion')\n**Abstraction Level**: base\n**Similarity Score**: 3.44\n**Source**: graph\n\n**Description**:\nCWE-843: Access of Resource Using Incompatible Type ('Type Confusion')\n\n**Mapping Guidance**:\n- Usage: Allowed\n- Rationale: This CWE entry is at the Base level of abstraction, which is a preferred level of abstraction for mapping to the root causes of vulnerabilities.\n\n**Relationships**:\n- CANPRECEDE -> CWE-119\n- CHILDOF -> CWE-704\n- CHILDOF -> CWE-704\n- PARENTOF -> CWE-843\n- PEEROF -> CWE-843\n\n\n\n## CWE-89: Improper Neutralization of Special Elements used in an SQL Command ('SQL Injection')\n**Abstraction Level**: base\n**Similarity Score**: 3.30\n**Source**: graph\n\n**Description**:\nCWE-89: Improper Neutralization of Special Elements used in an SQL Command ('SQL Injection')\n\n**Mapping Guidance**:\n- Usage: Allowed\n- Rationale: This CWE entry is at the Base level of abstraction, which is a preferred level of abstraction for mapping to the root causes of vulnerabilities.\n\n**Relationships**:\n- PARENTOF -> CWE-564\n- CANFOLLOW -> CWE-456\n- CHILDOF -> CWE-74\n- CHILDOF -> CWE-943\n- PARENTOF -> CWE-89\n\n\n\n## CWE-73: External Control of File Name or Path\n**Abstraction Level**: Base\n**Similarity Score**: 3.22\n**Source**: graph\n\n**Description**:\nThe product allows user input to control or influence paths or file names that are used in filesystem operations.\n\n**Mapping Guidance**:\n- Usage: Allowed\n- Rationale: This CWE entry is at the Base level of abstraction, which is a preferred level of abstraction for mapping to the root causes of vulnerabilities.\n\n**Relationships**:\n- PARENTOF -> CWE-114\n- CANPRECEDE -> CWE-5\n\n\n## CWE Relationship Analysis\n\nCurrent CWEs represent these abstraction levels: .\n\n\n### Vulnerability Chain Analysis\n\n**Chain starting from CWE-436:**\n- 436 (Interpretation Conflict) - ROOT\n\n\n**Chain starting from CWE-287:**\n- 287 (Improper Authentication) - ROOT\n\n\n\n### CWE Relationship Diagram\n\n```mermaid\ngraph TD\n    classDef primary fill:#f96,stroke:#333,stroke-width:2px\n    classDef secondary fill:#69f,stroke:#333\n    classDef tertiary fill:#9e9,stroke:#333\n```",
  "criticism": "",
  "resolution": "",
  "relevant_cwes": [
    {
      "metadata": {
        "doc_id": "89",
        "name": "Improper Neutralization of Special Elements used in an SQL Command ('SQL Injection')",
        "source": "sparse"
      },
      "similarity": 403.7086808504839
    },
    {
      "metadata": {
        "doc_id": "79",
        "name": "Improper Neutralization of Input During Web Page Generation ('Cross-site Scripting')",
        "source": "sparse"
      },
      "similarity": 402.48245895896366
    },
    {
      "metadata": {
        "doc_id": "306",
        "name": "Missing Authentication for Critical Function",
        "source": "sparse"
      },
      "similarity": 372.5186227499917
    },
    {
      "metadata": {
        "doc_id": "285",
        "name": "Improper Authorization",
        "source": "sparse"
      },
      "similarity": 362.39182826316426
    },
    {
      "metadata": {
        "doc_id": "266",
        "name": "Incorrect Privilege Assignment",
        "source": "sparse"
      },
      "similarity": 359.35614741811617
    },
    {
      "metadata": {
        "doc_id": "125",
        "name": "Out-of-bounds Read",
        "source": "sparse"
      },
      "similarity": 358.5020033477717
    },
    {
      "metadata": {
        "doc_id": "287",
        "name": "Improper Authentication",
        "source": "sparse"
      },
      "similarity": 355.0891392090893
    },
    {
      "metadata": {
        "doc_id": "22",
        "name": "Improper Limitation of a Pathname to a Restricted Directory ('Path Traversal')",
        "source": "sparse"
      },
      "similarity": 354.4401388692218
    },
    {
      "metadata": {
        "doc_id": "269",
        "name": "Improper Privilege Management",
        "type": "Class",
        "original_content": "The product does not properly assign, modify, track, or check privileges for an actor, creating an unintended sphere of control for that actor.",
        "keyphrase_source": "rootcause:improper access controls",
        "source": "dense",
        "mapping_notes": {
          "usage": "Discouraged",
          "rationale": "CWE-269 is commonly misused. It can be conflated with \"privilege escalation,\" which is a technical impact that is listed in many low-information vulnerability reports [REF-1287]. It is not useful for trend analysis.",
          "comments": "If an error or mistake allows privilege escalation, then use the CWE ID for that mistake. Avoid using CWE-269 when only phrases such as \"privilege escalation\" or \"gain privileges\" are available, as these indicate technical impact of the vulnerability - not the root cause weakness. If the root cause seems to be directly related to privileges, then examine the children of CWE-269 for additional hints, such as Execution with Unnecessary Privileges (CWE-250) or Incorrect Privilege Assignment (CWE-266).",
          "reasons": [
            "Frequent Misuse"
          ]
        },
        "score_info": {
          "retrievers": [
            "dense"
          ],
          "retriever_count": 1,
          "normalized_scores": {
            "dense": 0.6193283042242544
          }
        }
      },
      "similarity": 0.6193283042242544
    },
    {
      "doc_id": "73",
      "text": "The product allows user input to control or influence paths or file names that are used in filesystem operations.",
      "score": 0.6554406303135184,
      "metadata": {
        "doc_id": "73",
        "name": "External Control of File Name or Path",
        "type": "Base",
        "extended_description": "\n\nThis could allow an attacker to access or modify system files or other files that are critical to the application.\n\n\nPath manipulation errors occur when the following two conditions are met:\n\n```\n\t\t1. An attacker can specify a path used in an operation on the filesystem.\n\t\t2. By specifying the resource, the attacker gains a capability that would not otherwise be permitted.\n```\nFor example, the program may give the attacker the ability to overwrite the specified file or run with a configuration controlled by the attacker.",
        "alternate_terms": [],
        "original_content": "The product allows user input to control or influence paths or file names that are used in filesystem operations.",
        "relationships": [
          {
            "source_id": "73",
            "target_id": "114",
            "label": "PARENTOF",
            "properties": {
              "ordinal": "Primary",
              "view_id": "1000"
            }
          },
          {
            "source_id": "73",
            "target_id": "59",
            "label": "CANPRECEDE",
            "properties": {
              "view_id": "1000"
            }
          },
          {
            "source_id": "73",
            "target_id": "434",
            "label": "CANPRECEDE",
            "properties": {
              "view_id": "1000"
            }
          },
          {
            "source_id": "73",
            "target_id": "98",
            "label": "CANPRECEDE",
            "properties": {
              "view_id": "1000"
            }
          },
          {
            "source_id": "73",
            "target_id": "41",
            "label": "CANPRECEDE",
            "properties": {
              "view_id": "1000"
            }
          },
          {
            "source_id": "73",
            "target_id": "22",
            "label": "CANPRECEDE",
            "properties": {
              "view_id": "1000"
            }
          },
          {
            "source_id": "73",
            "target_id": "20",
            "label": "CHILDOF",
            "properties": {
              "ordinal": "Primary",
              "view_id": "700"
            }
          },
          {
            "source_id": "73",
            "target_id": "610",
            "label": "CHILDOF",
            "properties": {
              "view_id": "1000"
            }
          },
          {
            "source_id": "73",
            "target_id": "642",
            "label": "CHILDOF",
            "properties": {
              "ordinal": "Primary",
              "view_id": "1000"
            }
          },
          {
            "source_id": "99",
            "target_id": "73",
            "label": "CANALSOBE",
            "properties": {
              "view_id": "1000"
            }
          },
          {
            "source_id": "98",
            "target_id": "73",
            "label": "CANFOLLOW",
            "properties": {
              "view_id": "1000"
            }
          },
          {
            "source_id": "642",
            "target_id": "73",
            "label": "PARENTOF",
            "properties": {
              "ordinal": "Primary",
              "view_id": "1000"
            }
          },
          {
            "source_id": "610",
            "target_id": "73",
            "label": "PARENTOF",
            "properties": {
              "view_id": "1000"
            }
          },
          {
            "source_id": "59",
            "target_id": "73",
            "label": "CANFOLLOW",
            "properties": {
              "view_id": "1000"
            }
          },
          {
            "source_id": "434",
            "target_id": "73",
            "label": "CANFOLLOW",
            "properties": {
              "view_id": "1000"
            }
          },
          {
            "source_id": "41",
            "target_id": "73",
            "label": "CANFOLLOW",
            "properties": {
              "view_id": "1000"
            }
          },
          {
            "source_id": "22",
            "target_id": "73",
            "label": "CANFOLLOW",
            "properties": {
              "view_id": "1000"
            }
          },
          {
            "source_id": "20",
            "target_id": "73",
            "label": "PARENTOF",
            "properties": {
              "ordinal": "Primary",
              "view_id": "700"
            }
          },
          {
            "source_id": "114",
            "target_id": "73",
            "label": "CHILDOF",
            "properties": {
              "ordinal": "Primary",
              "view_id": "1000"
            }
          }
        ],
        "source": "graph",
        "sources": [
          "vector",
          "graph"
        ],
        "vector_score": 0.6554406303135184,
        "graph_score": 3.4200400000000006,
        "score_components": {
          "relationship_chain": 0.6,
          "explicit_mention": 1.0,
          "abstraction_path": 0.9,
          "sequence_path": 0.5760000000000002
        },
        "abstraction_factor": 1.3,
        "graph_path_info": {
          "path_types": [
            "relationship_chain",
            "vulnerability_sequence_forward"
          ],
          "best_paths": {
            "relationship_chain": {
              "path": [
                [
                  "79",
                  "184",
                  "CANFOLLOW"
                ],
                [
                  "184",
                  "98",
                  "CANPRECEDE"
                ],
                [
                  "98",
                  "73",
                  "CANFOLLOW"
                ]
              ],
              "score": 0.6,
              "type": "relationship_chain",
              "source": "79"
            },
            "vulnerability_sequence_forward": {
              "path": [
                [
                  "79",
                  "184",
                  "CANFOLLOW"
                ],
                [
                  "184",
                  "98",
                  "CANPRECEDE"
                ],
                [
                  "98",
                  "73",
                  "CANFOLLOW"
                ]
              ],
              "score": 0.5760000000000002,
              "type": "vulnerability_sequence_forward",
              "source": "79"
            }
          }
        },
        "is_explicit": true,
        "abstraction_level": "base",
        "position": "after",
        "mapping_notes": {
          "usage": "Allowed",
          "rationale": "This CWE entry is at the Base level of abstraction, which is a preferred level of abstraction for mapping to the root causes of vulnerabilities.",
          "comments": "Carefully read both the name and description to ensure that this mapping is an appropriate fit. Do not try to 'force' a mapping to a lower-level Base/Variant simply to comply with this preferred level of abstraction.",
          "reasons": [
            "Acceptable-Use"
          ]
        },
        "score_info": {
          "retrievers": [
            "dense",
            "graph"
          ],
          "retriever_count": 2,
          "normalized_scores": {
            "dense": 0.6146462331543946,
            "graph": 2.3142002521254077
          }
        }
      },
      "similarity": 2.3142002521254077
    }
  ],
  "identified_cwes": {
    "analyzer": [
      "CWE-436",
      "CWE-287",
      "CWE-172",
      "CWE-183",
      "CWE-346",
      "CWE-285",
      "CWE-98",
      "CWE-22",
      "CWE-552",
      "CWE-494",
      "CWE-41",
      "CWE-59",
      "CWE-184",
      "CWE-943",
      "CWE-24",
      "CWE-84",
      "CWE-456",
      "CWE-352",
      "CWE-83",
      "CWE-613",
      "CWE-87",
      "CWE-668",
      "CWE-73",
      "CWE-269",
      "CWE-669",
      "CWE-116",
      "CWE-430",
      "CWE-23",
      "CWE-473",
      "CWE-564",
      "CWE-114",
      "CWE-89",
      "CWE-5",
      "CWE-843",
      "CWE-79",
      "CWE-704",
      "CWE-863",
      "CWE-441",
      "CWE-85",
      "CWE-86",
      "CWE-20",
      "CWE-434",
      "CWE-306",
      "CWE-36",
      "CWE-425",
      "CWE-1275",
      "CWE-345",
      "CWE-642",
      "CWE-119",
      "CWE-74",
      "CWE-284"
    ],
    "critic_additional": []
  }
}