{
  "cve_id": "CVE-2024-10035",
  "description": "**Improper Control of Generation of Code (Code Injection)** vulnerability in BG-TEK Informatics Security Technologies CoslatV3 allows Command Injection.This issue affects CoslatV3 through 3.1069. NOTE The vendor was contacted and it was learned that the product is not supported.",
  "key_phrases": {
    "rootcause": "Improper Control of Generation of Code (Code Injection)",
    "weakness": "command injection",
    "impact": "",
    "vector": "",
    "attacker": "",
    "product": "BG-TEK Informatics Security Technologies CoslatV3",
    "version": "through 3.1069",
    "component": ""
  },
  "reference_content": null,
  "similar_info": {
    "cwe_distribution": {},
    "cwe_consensus": "",
    "similarity_stats": {
      "thresholds": [],
      "total_samples_by_threshold": {},
      "top_cwes_by_threshold": {}
    }
  },
  "similarity_summary": {
    "consensus_cwe": "",
    "top_cwes": [],
    "confidence_levels": {},
    "total_samples": 0
  },
  "analysis": "# Summary\n| CWE ID | CWE Name | Confidence | CWE Abstraction Level | CWE Vulnerability Mapping Label | CWE-Vulnerability Mapping Notes |\n|---|---|---|---|---|---|\n| CWE-94 | Improper Control of Generation of Code ('Code Injection') | 1.0 | Base | Allowed-with-Review | Primary CWE: The vulnerability description explicitly states \"Improper Control of Generation of Code (Code Injection) vulnerability\". |\n| CWE-78 | Improper Neutralization of Special Elements used in an OS Command ('OS Command Injection') | 0.7 | Base | Allowed | Secondary CWE: The vulnerability description mentions \"command injection,\" which is closely related to OS command injection. |\n\n## Evidence and Confidence\n\n*   **Confidence Score:** 0.9\n*   **Evidence Strength:** HIGH\n\n## Relationship Analysis\nThe primary CWE is CWE-94, which is a base-level CWE. The secondary CWE is CWE-78, which is also a base-level CWE. CWE-78 is a child of CWE-77, which is a class-level CWE. CWE-94 is child of CWE-74 and CWE-913.\n\n```mermaid\ngraph TD\n    cwe94[\"CWE-94: Improper Control of Generation of Code ('Code Injection')\"]\n    cwe78[\"CWE-78: Improper Neutralization of Special Elements used in an OS Command ('OS Command Injection')\"]\n    cwe77[\"CWE-77: Improper Neutralization of Special Elements used in a Command ('Command Injection')\"]\n    cwe74[\"CWE-74: Improper Neutralization of Special Elements in Output Used by a Downstream Component ('Injection')\"]\n    cwe913[\"CWE-913: Improper Control of Dynamically-Managed Code Resources\"]\n    \n    cwe78 -->|CHILDOF| cwe77\n    cwe94 -->|CHILDOF| cwe74\n    cwe94 -->|CHILDOF| cwe913\n    \n    classDef primary fill:#f96,stroke:#333,stroke-width:2px\n    classDef secondary fill:#69f,stroke:#333\n    classDef tertiary fill:#9e9,stroke:#333\n    class cwe94 primary\n    class cwe78 secondary\n    class cwe77,cwe74,cwe913 tertiary\n```\n\n## Vulnerability Chain\nThe vulnerability chain starts with **Improper Control of Generation of Code (Code Injection)**, leading to **command injection**.\n\n## Summary of Analysis\nThe primary CWE is CWE-94 because the vulnerability description explicitly states **\"Improper Control of Generation of Code (Code Injection) vulnerability\"**. The secondary CWE is CWE-78 because the vulnerability description mentions **\"command injection\"**, which is closely related to OS command injection. The confidence score is high because the vulnerability description explicitly states the CWE. The evidence strength is high because the vulnerability description explicitly states the CWE.\n\nThe vulnerability description explicitly states **\"Improper Control of Generation of Code (Code Injection) vulnerability in BG-TEK Informatics Security Technologies CoslatV3 allows Command Injection.\"** This statement clearly indicates that the root cause of the vulnerability is **Improper Control of Generation of Code (Code Injection)**, which is CWE-94. The vulnerability also allows **Command Injection**, which is closely related to OS command injection.\n\nRelevant CWE Information:\n\n# Enhanced Context (25 CWEs)\nThe following CWEs were identified as potentially relevant to this vulnerability:\n\n## CWE-74: Improper Neutralization of Special Elements in Output Used by a Downstream Component ('Injection')\n**Abstraction Level**: Class\n**Similarity Score**: 0.76\n**Source**: dense\n\n**Description**:\nThe product constructs all or part of a command, data structure, or record using externally-influenced input from an upstream component, but it does not neutralize or incorrectly neutralizes special elements that could modify how it is parsed or interpreted when it is sent to a downstream component.\n\n**Mapping Guidance**:\n- Usage: Discouraged\n- Rationale: CWE-74 is high-level and often misused when lower-level weaknesses are more appropriate.\n\n## CWE-80: Improper Neutralization of Script-Related HTML Tags in a Web Page (Basic XSS)\n**Abstraction Level**: Variant\n**Similarity Score**: 0.76\n**Source**: dense\n\n**Description**:\nThe product receives input from an upstream component, but it does not neutralize or incorrectly neutralizes special characters such as \"<\", \">\", and \"&\" that could be interpreted as web-scripting elements when they are sent to a downstream component that processes web pages.\n\n**Mapping Guidance**:\n- Usage: Allowed\n- Rationale: This CWE entry is at the Variant level of abstraction, which is a preferred level of abstraction for mapping to the root causes of vulnerabilities.\n\n## CWE-917: Improper Neutralization of Special Elements used in an Expression Language Statement ('Expression Language Injection')\n**Abstraction Level**: Base\n**Similarity Score**: 0.75\n**Source**: dense\n\n**Description**:\nThe product constructs all or part of an expression language (EL) statement in a framework such as a Java Server Page (JSP) using externally-influenced input from an upstream component, but it does not neutralize or incorrectly neutralizes special elements that could modify the intended EL statement before it is executed.\n\n**Mapping Guidance**:\n- Usage: Allowed\n- Rationale: This CWE entry is at the Base level of abstraction, which is a preferred level of abstraction for mapping to the root causes of vulnerabilities.\n\n## CWE-943: Improper Neutralization of Special Elements in Data Query Logic\n**Abstraction Level**: Class\n**Similarity Score**: 0.74\n**Source**: dense\n\n**Description**:\nThe product generates a query intended to access or manipulate data in a data store such as a database, but it does not neutralize or incorrectly neutralizes special elements that can modify the intended logic of the query.\n\n**Mapping Guidance**:\n- Usage: Allowed-with-Review\n- Rationale: This CWE entry is a Class and might have Base-level children that would be more appropriate\n\n## CWE-88: Improper Neutralization of Argument Delimiters in a Command ('Argument Injection')\n**Abstraction Level**: Base\n**Similarity Score**: 0.73\n**Source**: dense\n\n**Description**:\nThe product constructs a string for a command to be executed by a separate component\nin another control sphere, but it does not properly delimit the\nintended arguments, options, or switches within that command string.\n\n**Mapping Guidance**:\n- Usage: Allowed\n- Rationale: This CWE entry is at the Base level of abstraction, which is a preferred level of abstraction for mapping to the root causes of vulnerabilities.\n\n## CWE-138: Improper Neutralization of Special Elements\n**Abstraction Level**: Class\n**Similarity Score**: 0.73\n**Source**: dense\n\n**Description**:\nThe product receives input from an upstream component, but it does not neutralize or incorrectly neutralizes special elements that could be interpreted as control elements or syntactic markers when they are sent to a downstream component.\n\n**Mapping Guidance**:\n- Usage: Discouraged\n- Rationale: This CWE entry is a level-1 Class (i.e., a child of a Pillar). It might have lower-level children that would be more appropriate\n\n## CWE-184: Incomplete List of Disallowed Inputs\n**Abstraction Level**: Base\n**Similarity Score**: 0.72\n**Source**: dense\n\n**Description**:\nThe product implements a protection mechanism that relies on a list of inputs (or properties of inputs) that are not allowed by policy or otherwise require other action to neutralize before additional processing takes place, but the list is incomplete.\n\n**Mapping Guidance**:\n- Usage: Allowed\n- Rationale: This CWE entry is at the Base level of abstraction, which is a preferred level of abstraction for mapping to the root causes of vulnerabilities.\n\n## CWE-1236: Improper Neutralization of Formula Elements in a CSV File\n**Abstraction Level**: Base\n**Similarity Score**: 0.72\n**Source**: dense\n\n**Description**:\nThe product saves user-provided information into a Comma-Separated Value (CSV) file, but it does not neutralize or incorrectly neutralizes special elements that could be interpreted as a command when the file is opened by a spreadsheet product.\n\n**Mapping Guidance**:\n- Usage: Allowed\n- Rationale: This CWE entry is at the Base level of abstraction, which is a preferred level of abstraction for mapping to the root causes of vulnerabilities.\n\n## CWE-116: Improper Encoding or Escaping of Output\n**Abstraction Level**: Class\n**Similarity Score**: 0.72\n**Source**: dense\n\n**Description**:\nThe product prepares a structured message for communication with another component, but encoding or escaping of the data is either missing or done incorrectly. As a result, the intended structure of the message is not preserved.\n\n**Mapping Guidance**:\n- Usage: Allowed-with-Review\n- Rationale: This CWE entry is a Class and might have Base-level children that would be more appropriate\n\n## CWE-1289: Improper Validation of Unsafe Equivalence in Input\n**Abstraction Level**: Base\n**Similarity Score**: 0.72\n**Source**: dense\n\n**Description**:\nThe product receives an input value that is used as a resource identifier or other type of reference, but it does not validate or incorrectly validates that the input is equivalent to a potentially-unsafe value.\n\n**Mapping Guidance**:\n- Usage: Allowed\n- Rationale: This CWE entry is at the Base level of abstraction, which is a preferred level of abstraction for mapping to the root causes of vulnerabilities.\n\n## CWE-88: Improper Neutralization of Argument Delimiters in a Command ('Argument Injection')\n**Abstraction Level**: Base\n**Similarity Score**: 8028.46\n**Source**: sparse\n\n**Description**:\nThe product constructs a string for a command to be executed by a separate component\nin another control sphere, but it does not properly delimit the\nintended arguments, options, or switches within that command string.\n\n**Mapping Guidance**:\n- Usage: Allowed\n- Rationale: This CWE entry is at the Base level of abstraction, which is a preferred level of abstraction for mapping to the root causes of vulnerabilities.\n\n## CWE-79: Improper Neutralization of Input During Web Page Generation ('Cross-site Scripting')\n**Abstraction Level**: Base\n**Similarity Score**: 7962.74\n**Source**: sparse\n\n**Description**:\nThe product does not neutralize or incorrectly neutralizes user-controllable input before it is placed in output that is used as a web page that is served to other users.\n\n**Mapping Guidance**:\n- Usage: Allowed\n- Rationale: This CWE entry is at the Base level of abstraction, which is a preferred level of abstraction for mapping to the root causes of vulnerabilities.\n\n## CWE-116: Improper Encoding or Escaping of Output\n**Abstraction Level**: Class\n**Similarity Score**: 7907.87\n**Source**: sparse\n\n**Description**:\nThe product prepares a structured message for communication with another component, but encoding or escaping of the data is either missing or done incorrectly. As a result, the intended structure of the message is not preserved.\n\n**Mapping Guidance**:\n- Usage: Allowed-with-Review\n- Rationale: This CWE entry is a Class and might have Base-level children that would be more appropriate\n\n## CWE-138: Improper Neutralization of Special Elements\n**Abstraction Level**: Class\n**Similarity Score**: 7845.87\n**Source**: sparse\n\n**Description**:\nThe product receives input from an upstream component, but it does not neutralize or incorrectly neutralizes special elements that could be interpreted as control elements or syntactic markers when they are sent to a downstream component.\n\n**Mapping Guidance**:\n- Usage: Discouraged\n- Rationale: This CWE entry is a level-1 Class (i.e., a child of a Pillar). It might have lower-level children that would be more appropriate\n\n## CWE-95: Improper Neutralization of Directives in Dynamically Evaluated Code ('Eval Injection')\n**Abstraction Level**: Variant\n**Similarity Score**: 7764.02\n**Source**: sparse\n\n**Description**:\nThe product receives input from an upstream component, but it does not neutralize or incorrectly neutralizes code syntax before using the input in a dynamic evaluation call (e.g. \"eval\").\n\n**Mapping Guidance**:\n- Usage: Allowed\n- Rationale: This CWE entry is at the Variant level of abstraction, which is a preferred level of abstraction for mapping to the root causes of vulnerabilities.\n\n## CWE-78: Improper Neutralization of Special Elements used in an OS Command ('OS Command Injection')\n**Abstraction Level**: base\n**Similarity Score**: 4.47\n**Source**: graph\n\n**Description**:\nCWE-78: Improper Neutralization of Special Elements used in an OS Command ('OS Command Injection')\n\n**Mapping Guidance**:\n- Usage: Allowed\n- Rationale: This CWE entry is at the Base level of abstraction, which is a preferred level of abstraction for mapping to the root causes of vulnerabilities.\n\n**Relationships**:\n- CANFOLLOW -> CWE-184\n- CANALSOBE -> CWE-88\n- CHILDOF -> CWE-77\n- CHILDOF -> CWE-77\n- CHILDOF -> CWE-74\n\n## CWE-494: Download of Code Without Integrity Check\n**Abstraction Level**: base\n**Similarity Score**: 4.33\n**Source**: graph\n\n**Description**:\nCWE-494: Download of Code Without Integrity Check\n\n**Mapping Guidance**:\n- Usage: Allowed\n- Rationale: This CWE entry is at the Base level of abstraction, which is a preferred level of abstraction for mapping to the root causes of vulnerabilities.\n\n**Relationships**:\n- CANFOLLOW -> CWE-79\n- CHILDOF -> CWE-669\n- CHILDOF -> CWE-669\n- CHILDOF -> CWE-345\n- CANPRECEDE -> CWE-494\n\n## CWE-183: Permissive List of Allowed Inputs\n**Abstraction Level**: base\n**Similarity Score**: 4.24\n**Source**: graph\n\n**Description**:\nCWE-183: Permissive List of Allowed Inputs\n\n**Mapping Guidance**:\n- Usage: Allowed\n- Rationale: This CWE entry is at the Base level of abstraction, which is a preferred level of abstraction for mapping to the root causes of vulnerabilities.\n\n**Relationships**:\n- PARENTOF -> CWE-942\n- CANPRECEDE -> CWE-434\n- CHILDOF -> CWE-697\n- CHILDOF -> CWE-183\n- PARENTOF -> CWE-183\n\n## CWE-625: Permissive Regular Expression\n**Abstraction Level**: base\n**Similarity Score**: 3.64\n**Source**: graph\n\n**Description**:\nCWE-625: Permissive Regular Expression\n\n**Mapping Guidance**:\n- Usage: Allowed\n- Rationale: This CWE entry is at the Base level of abstraction, which is a preferred level of abstraction for mapping to the root causes of vulnerabilities.\n\n**Relationships**:\n- PARENTOF -> CWE-777\n- PEEROF -> CWE-183\n- PEEROF -> CWE-184\n- PEEROF -> CWE-187\n- CHILDOF -> CWE-185\n\n## CWE-915: Improperly Controlled Modification of Dynamically-Determined Object Attributes\n**Abstraction Level**: base\n**Similarity Score**: 3.64\n**Source**: graph\n\n**Description**:\nCWE-915: Improperly Controlled Modification of Dynamically-Determined Object Attributes\n\n**Mapping Guidance**:\n- Usage: Allowed\n- Rationale: This CWE entry is at the Base level of abstraction, which is a preferred level of abstraction for mapping to the root causes of vulnerabilities.\n\n**Relationships**:\n- PARENTOF -> CWE-1321\n- PEEROF -> CWE-502\n- CHILDOF -> CWE-913\n- PARENTOF -> CWE-915\n- PEEROF -> CWE-915\n\n## CWE-94: Improper Control of Generation of Code ('Code Injection')\n**Abstraction Level**: base\n**Similarity Score**: 3.49\n**Source**: graph\n\n**Description**:\nCWE-94: Improper Control of Generation of Code ('Code Injection')\n\n**Mapping Guidance**:\n- Usage: Allowed-with-Review\n- Rationale: This entry is frequently misused for vulnerabilities with a technical impact of \"code execution,\" which does not by itself indicate a root cause weakness, since dozens of weaknesses can enable code execution.\n\n**Relationships**:\n- CANFOLLOW -> CWE-98\n- PARENTOF -> CWE-96\n- PARENTOF -> CWE-95\n- PARENTOF -> CWE-1336\n- CHILDOF -> CWE-913\n\n## CWE-79: Improper Neutralization of Input During Web Page Generation ('Cross-site Scripting')\n**Abstraction Level**: Base\n**Similarity Score**: 3.30\n**Source**: graph\n\n**Description**:\nThe product does not neutralize or incorrectly neutralizes user-controllable input before it is placed in output that is used as a web page that is served to other users.\n\n**Mapping Guidance**:\n- Usage: Allowed\n- Rationale: This CWE entry is at the Base level of abstraction, which is a preferred level of abstraction for mapping to the root causes of vulnerabilities.\n\n**Relationships**:\n- PARENTOF -> CWE-87\n- PARENTOF -> CWE-86\n- PARENTOF -> CWE-85\n- PARENTOF -> CWE-84\n- PARENTOF -> CWE-83\n\n## CWE-426: Untrusted Search Path\n**Abstraction Level**: base\n**Similarity Score**: 2.77\n**Source**: graph\n\n**Description**:\nCWE-426: Untrusted Search Path\n\n**Mapping Guidance**:\n- Usage: Allowed\n- Rationale: This CWE entry is at the Base level of abstraction, which is a preferred level of abstraction for mapping to the root causes of vulnerabilities.\n\n**Relationships**:\n- PEEROF -> CWE-428\n- PEEROF -> CWE-427\n- CHILDOF -> CWE-673\n- CHILDOF -> CWE-668\n- CHILDOF -> CWE-642\n\n## CWE-98: Improper Control of Filename for Include/Require Statement in PHP Program ('PHP Remote File Inclusion')\n**Abstraction Level**: variant\n**Similarity Score**: 2.69\n**Source**: graph\n\n**Description**:\nCWE-98: Improper Control",
  "analysis_with_relationships": "# Summary\n| CWE ID | CWE Name | Confidence | CWE Abstraction Level | CWE Vulnerability Mapping Label | CWE-Vulnerability Mapping Notes |\n|---|---|---|---|---|---|\n| CWE-94 | Improper Control of Generation of Code ('Code Injection') | 1.0 | Base | Allowed-with-Review | Primary CWE: The vulnerability description explicitly states \"Improper Control of Generation of Code (Code Injection) vulnerability\". |\n| CWE-78 | Improper Neutralization of Special Elements used in an OS Command ('OS Command Injection') | 0.7 | Base | Allowed | Secondary CWE: The vulnerability description mentions \"command injection,\" which is closely related to OS command injection. |\n\n## Evidence and Confidence\n\n*   **Confidence Score:** 0.9\n*   **Evidence Strength:** HIGH\n\n## Relationship Analysis\nThe primary CWE is CWE-94, which is a base-level CWE. The secondary CWE is CWE-78, which is also a base-level CWE. CWE-78 is a child of CWE-77, which is a class-level CWE. CWE-94 is child of CWE-74 and CWE-913.\n\n```mermaid\ngraph TD\n    cwe94[\"CWE-94: Improper Control of Generation of Code ('Code Injection')\"]\n    cwe78[\"CWE-78: Improper Neutralization of Special Elements used in an OS Command ('OS Command Injection')\"]\n    cwe77[\"CWE-77: Improper Neutralization of Special Elements used in a Command ('Command Injection')\"]\n    cwe74[\"CWE-74: Improper Neutralization of Special Elements in Output Used by a Downstream Component ('Injection')\"]\n    cwe913[\"CWE-913: Improper Control of Dynamically-Managed Code Resources\"]\n    \n    cwe78 -->|CHILDOF| cwe77\n    cwe94 -->|CHILDOF| cwe74\n    cwe94 -->|CHILDOF| cwe913\n    \n    classDef primary fill:#f96,stroke:#333,stroke-width:2px\n    classDef secondary fill:#69f,stroke:#333\n    classDef tertiary fill:#9e9,stroke:#333\n    class cwe94 primary\n    class cwe78 secondary\n    class cwe77,cwe74,cwe913 tertiary\n```\n\n## Vulnerability Chain\nThe vulnerability chain starts with **Improper Control of Generation of Code (Code Injection)**, leading to **command injection**.\n\n## Summary of Analysis\nThe primary CWE is CWE-94 because the vulnerability description explicitly states **\"Improper Control of Generation of Code (Code Injection) vulnerability\"**. The secondary CWE is CWE-78 because the vulnerability description mentions **\"command injection\"**, which is closely related to OS command injection. The confidence score is high because the vulnerability description explicitly states the CWE. The evidence strength is high because the vulnerability description explicitly states the CWE.\n\nThe vulnerability description explicitly states **\"Improper Control of Generation of Code (Code Injection) vulnerability in BG-TEK Informatics Security Technologies CoslatV3 allows Command Injection.\"** This statement clearly indicates that the root cause of the vulnerability is **Improper Control of Generation of Code (Code Injection)**, which is CWE-94. The vulnerability also allows **Command Injection**, which is closely related to OS command injection.\n\nRelevant CWE Information:\n\n# Enhanced Context (25 CWEs)\nThe following CWEs were identified as potentially relevant to this vulnerability:\n\n## CWE-74: Improper Neutralization of Special Elements in Output Used by a Downstream Component ('Injection')\n**Abstraction Level**: Class\n**Similarity Score**: 0.76\n**Source**: dense\n\n**Description**:\nThe product constructs all or part of a command, data structure, or record using externally-influenced input from an upstream component, but it does not neutralize or incorrectly neutralizes special elements that could modify how it is parsed or interpreted when it is sent to a downstream component.\n\n**Mapping Guidance**:\n- Usage: Discouraged\n- Rationale: CWE-74 is high-level and often misused when lower-level weaknesses are more appropriate.\n\n## CWE-80: Improper Neutralization of Script-Related HTML Tags in a Web Page (Basic XSS)\n**Abstraction Level**: Variant\n**Similarity Score**: 0.76\n**Source**: dense\n\n**Description**:\nThe product receives input from an upstream component, but it does not neutralize or incorrectly neutralizes special characters such as \"<\", \">\", and \"&\" that could be interpreted as web-scripting elements when they are sent to a downstream component that processes web pages.\n\n**Mapping Guidance**:\n- Usage: Allowed\n- Rationale: This CWE entry is at the Variant level of abstraction, which is a preferred level of abstraction for mapping to the root causes of vulnerabilities.\n\n## CWE-917: Improper Neutralization of Special Elements used in an Expression Language Statement ('Expression Language Injection')\n**Abstraction Level**: Base\n**Similarity Score**: 0.75\n**Source**: dense\n\n**Description**:\nThe product constructs all or part of an expression language (EL) statement in a framework such as a Java Server Page (JSP) using externally-influenced input from an upstream component, but it does not neutralize or incorrectly neutralizes special elements that could modify the intended EL statement before it is executed.\n\n**Mapping Guidance**:\n- Usage: Allowed\n- Rationale: This CWE entry is at the Base level of abstraction, which is a preferred level of abstraction for mapping to the root causes of vulnerabilities.\n\n## CWE-943: Improper Neutralization of Special Elements in Data Query Logic\n**Abstraction Level**: Class\n**Similarity Score**: 0.74\n**Source**: dense\n\n**Description**:\nThe product generates a query intended to access or manipulate data in a data store such as a database, but it does not neutralize or incorrectly neutralizes special elements that can modify the intended logic of the query.\n\n**Mapping Guidance**:\n- Usage: Allowed-with-Review\n- Rationale: This CWE entry is a Class and might have Base-level children that would be more appropriate\n\n## CWE-88: Improper Neutralization of Argument Delimiters in a Command ('Argument Injection')\n**Abstraction Level**: Base\n**Similarity Score**: 0.73\n**Source**: dense\n\n**Description**:\nThe product constructs a string for a command to be executed by a separate component\nin another control sphere, but it does not properly delimit the\nintended arguments, options, or switches within that command string.\n\n**Mapping Guidance**:\n- Usage: Allowed\n- Rationale: This CWE entry is at the Base level of abstraction, which is a preferred level of abstraction for mapping to the root causes of vulnerabilities.\n\n## CWE-138: Improper Neutralization of Special Elements\n**Abstraction Level**: Class\n**Similarity Score**: 0.73\n**Source**: dense\n\n**Description**:\nThe product receives input from an upstream component, but it does not neutralize or incorrectly neutralizes special elements that could be interpreted as control elements or syntactic markers when they are sent to a downstream component.\n\n**Mapping Guidance**:\n- Usage: Discouraged\n- Rationale: This CWE entry is a level-1 Class (i.e., a child of a Pillar). It might have lower-level children that would be more appropriate\n\n## CWE-184: Incomplete List of Disallowed Inputs\n**Abstraction Level**: Base\n**Similarity Score**: 0.72\n**Source**: dense\n\n**Description**:\nThe product implements a protection mechanism that relies on a list of inputs (or properties of inputs) that are not allowed by policy or otherwise require other action to neutralize before additional processing takes place, but the list is incomplete.\n\n**Mapping Guidance**:\n- Usage: Allowed\n- Rationale: This CWE entry is at the Base level of abstraction, which is a preferred level of abstraction for mapping to the root causes of vulnerabilities.\n\n## CWE-1236: Improper Neutralization of Formula Elements in a CSV File\n**Abstraction Level**: Base\n**Similarity Score**: 0.72\n**Source**: dense\n\n**Description**:\nThe product saves user-provided information into a Comma-Separated Value (CSV) file, but it does not neutralize or incorrectly neutralizes special elements that could be interpreted as a command when the file is opened by a spreadsheet product.\n\n**Mapping Guidance**:\n- Usage: Allowed\n- Rationale: This CWE entry is at the Base level of abstraction, which is a preferred level of abstraction for mapping to the root causes of vulnerabilities.\n\n## CWE-116: Improper Encoding or Escaping of Output\n**Abstraction Level**: Class\n**Similarity Score**: 0.72\n**Source**: dense\n\n**Description**:\nThe product prepares a structured message for communication with another component, but encoding or escaping of the data is either missing or done incorrectly. As a result, the intended structure of the message is not preserved.\n\n**Mapping Guidance**:\n- Usage: Allowed-with-Review\n- Rationale: This CWE entry is a Class and might have Base-level children that would be more appropriate\n\n## CWE-1289: Improper Validation of Unsafe Equivalence in Input\n**Abstraction Level**: Base\n**Similarity Score**: 0.72\n**Source**: dense\n\n**Description**:\nThe product receives an input value that is used as a resource identifier or other type of reference, but it does not validate or incorrectly validates that the input is equivalent to a potentially-unsafe value.\n\n**Mapping Guidance**:\n- Usage: Allowed\n- Rationale: This CWE entry is at the Base level of abstraction, which is a preferred level of abstraction for mapping to the root causes of vulnerabilities.\n\n## CWE-88: Improper Neutralization of Argument Delimiters in a Command ('Argument Injection')\n**Abstraction Level**: Base\n**Similarity Score**: 8028.46\n**Source**: sparse\n\n**Description**:\nThe product constructs a string for a command to be executed by a separate component\nin another control sphere, but it does not properly delimit the\nintended arguments, options, or switches within that command string.\n\n**Mapping Guidance**:\n- Usage: Allowed\n- Rationale: This CWE entry is at the Base level of abstraction, which is a preferred level of abstraction for mapping to the root causes of vulnerabilities.\n\n## CWE-79: Improper Neutralization of Input During Web Page Generation ('Cross-site Scripting')\n**Abstraction Level**: Base\n**Similarity Score**: 7962.74\n**Source**: sparse\n\n**Description**:\nThe product does not neutralize or incorrectly neutralizes user-controllable input before it is placed in output that is used as a web page that is served to other users.\n\n**Mapping Guidance**:\n- Usage: Allowed\n- Rationale: This CWE entry is at the Base level of abstraction, which is a preferred level of abstraction for mapping to the root causes of vulnerabilities.\n\n## CWE-116: Improper Encoding or Escaping of Output\n**Abstraction Level**: Class\n**Similarity Score**: 7907.87\n**Source**: sparse\n\n**Description**:\nThe product prepares a structured message for communication with another component, but encoding or escaping of the data is either missing or done incorrectly. As a result, the intended structure of the message is not preserved.\n\n**Mapping Guidance**:\n- Usage: Allowed-with-Review\n- Rationale: This CWE entry is a Class and might have Base-level children that would be more appropriate\n\n## CWE-138: Improper Neutralization of Special Elements\n**Abstraction Level**: Class\n**Similarity Score**: 7845.87\n**Source**: sparse\n\n**Description**:\nThe product receives input from an upstream component, but it does not neutralize or incorrectly neutralizes special elements that could be interpreted as control elements or syntactic markers when they are sent to a downstream component.\n\n**Mapping Guidance**:\n- Usage: Discouraged\n- Rationale: This CWE entry is a level-1 Class (i.e., a child of a Pillar). It might have lower-level children that would be more appropriate\n\n## CWE-95: Improper Neutralization of Directives in Dynamically Evaluated Code ('Eval Injection')\n**Abstraction Level**: Variant\n**Similarity Score**: 7764.02\n**Source**: sparse\n\n**Description**:\nThe product receives input from an upstream component, but it does not neutralize or incorrectly neutralizes code syntax before using the input in a dynamic evaluation call (e.g. \"eval\").\n\n**Mapping Guidance**:\n- Usage: Allowed\n- Rationale: This CWE entry is at the Variant level of abstraction, which is a preferred level of abstraction for mapping to the root causes of vulnerabilities.\n\n## CWE-78: Improper Neutralization of Special Elements used in an OS Command ('OS Command Injection')\n**Abstraction Level**: base\n**Similarity Score**: 4.47\n**Source**: graph\n\n**Description**:\nCWE-78: Improper Neutralization of Special Elements used in an OS Command ('OS Command Injection')\n\n**Mapping Guidance**:\n- Usage: Allowed\n- Rationale: This CWE entry is at the Base level of abstraction, which is a preferred level of abstraction for mapping to the root causes of vulnerabilities.\n\n**Relationships**:\n- CANFOLLOW -> CWE-184\n- CANALSOBE -> CWE-88\n- CHILDOF -> CWE-77\n- CHILDOF -> CWE-77\n- CHILDOF -> CWE-74\n\n## CWE-494: Download of Code Without Integrity Check\n**Abstraction Level**: base\n**Similarity Score**: 4.33\n**Source**: graph\n\n**Description**:\nCWE-494: Download of Code Without Integrity Check\n\n**Mapping Guidance**:\n- Usage: Allowed\n- Rationale: This CWE entry is at the Base level of abstraction, which is a preferred level of abstraction for mapping to the root causes of vulnerabilities.\n\n**Relationships**:\n- CANFOLLOW -> CWE-79\n- CHILDOF -> CWE-669\n- CHILDOF -> CWE-669\n- CHILDOF -> CWE-345\n- CANPRECEDE -> CWE-494\n\n## CWE-183: Permissive List of Allowed Inputs\n**Abstraction Level**: base\n**Similarity Score**: 4.24\n**Source**: graph\n\n**Description**:\nCWE-183: Permissive List of Allowed Inputs\n\n**Mapping Guidance**:\n- Usage: Allowed\n- Rationale: This CWE entry is at the Base level of abstraction, which is a preferred level of abstraction for mapping to the root causes of vulnerabilities.\n\n**Relationships**:\n- PARENTOF -> CWE-942\n- CANPRECEDE -> CWE-434\n- CHILDOF -> CWE-697\n- CHILDOF -> CWE-183\n- PARENTOF -> CWE-183\n\n## CWE-625: Permissive Regular Expression\n**Abstraction Level**: base\n**Similarity Score**: 3.64\n**Source**: graph\n\n**Description**:\nCWE-625: Permissive Regular Expression\n\n**Mapping Guidance**:\n- Usage: Allowed\n- Rationale: This CWE entry is at the Base level of abstraction, which is a preferred level of abstraction for mapping to the root causes of vulnerabilities.\n\n**Relationships**:\n- PARENTOF -> CWE-777\n- PEEROF -> CWE-183\n- PEEROF -> CWE-184\n- PEEROF -> CWE-187\n- CHILDOF -> CWE-185\n\n## CWE-915: Improperly Controlled Modification of Dynamically-Determined Object Attributes\n**Abstraction Level**: base\n**Similarity Score**: 3.64\n**Source**: graph\n\n**Description**:\nCWE-915: Improperly Controlled Modification of Dynamically-Determined Object Attributes\n\n**Mapping Guidance**:\n- Usage: Allowed\n- Rationale: This CWE entry is at the Base level of abstraction, which is a preferred level of abstraction for mapping to the root causes of vulnerabilities.\n\n**Relationships**:\n- PARENTOF -> CWE-1321\n- PEEROF -> CWE-502\n- CHILDOF -> CWE-913\n- PARENTOF -> CWE-915\n- PEEROF -> CWE-915\n\n## CWE-94: Improper Control of Generation of Code ('Code Injection')\n**Abstraction Level**: base\n**Similarity Score**: 3.49\n**Source**: graph\n\n**Description**:\nCWE-94: Improper Control of Generation of Code ('Code Injection')\n\n**Mapping Guidance**:\n- Usage: Allowed-with-Review\n- Rationale: This entry is frequently misused for vulnerabilities with a technical impact of \"code execution,\" which does not by itself indicate a root cause weakness, since dozens of weaknesses can enable code execution.\n\n**Relationships**:\n- CANFOLLOW -> CWE-98\n- PARENTOF -> CWE-96\n- PARENTOF -> CWE-95\n- PARENTOF -> CWE-1336\n- CHILDOF -> CWE-913\n\n## CWE-79: Improper Neutralization of Input During Web Page Generation ('Cross-site Scripting')\n**Abstraction Level**: Base\n**Similarity Score**: 3.30\n**Source**: graph\n\n**Description**:\nThe product does not neutralize or incorrectly neutralizes user-controllable input before it is placed in output that is used as a web page that is served to other users.\n\n**Mapping Guidance**:\n- Usage: Allowed\n- Rationale: This CWE entry is at the Base level of abstraction, which is a preferred level of abstraction for mapping to the root causes of vulnerabilities.\n\n**Relationships**:\n- PARENTOF -> CWE-87\n- PARENTOF -> CWE-86\n- PARENTOF -> CWE-85\n- PARENTOF -> CWE-84\n- PARENTOF -> CWE-83\n\n## CWE-426: Untrusted Search Path\n**Abstraction Level**: base\n**Similarity Score**: 2.77\n**Source**: graph\n\n**Description**:\nCWE-426: Untrusted Search Path\n\n**Mapping Guidance**:\n- Usage: Allowed\n- Rationale: This CWE entry is at the Base level of abstraction, which is a preferred level of abstraction for mapping to the root causes of vulnerabilities.\n\n**Relationships**:\n- PEEROF -> CWE-428\n- PEEROF -> CWE-427\n- CHILDOF -> CWE-673\n- CHILDOF -> CWE-668\n- CHILDOF -> CWE-642\n\n## CWE-98: Improper Control of Filename for Include/Require Statement in PHP Program ('PHP Remote File Inclusion')\n**Abstraction Level**: variant\n**Similarity Score**: 2.69\n**Source**: graph\n\n**Description**:\nCWE-98: Improper Control\n\n\n## CWE Relationship Analysis\n\nCurrent CWEs represent these abstraction levels: .\n\n\n### Vulnerability Chain Analysis\n\n**Chain starting from CWE-777:**\n- 777 (Regular Expression without Anchors) - ROOT\n\n\n**Chain starting from CWE-697:**\n- 697 (Incorrect Comparison) - ROOT\n\n\n\n### CWE Relationship Diagram\n\n```mermaid\ngraph TD\n    classDef primary fill:#f96,stroke:#333,stroke-width:2px\n    classDef secondary fill:#69f,stroke:#333\n    classDef tertiary fill:#9e9,stroke:#333\n```",
  "criticism": "",
  "resolution": "",
  "relevant_cwes": [
    {
      "metadata": {
        "doc_id": "77",
        "name": "Improper Neutralization of Special Elements used in a Command ('Command Injection')",
        "source": "alternate_terms",
        "original_matched_text": "AlternateTerms: Command injection",
        "match_reason": "exact_match_whole_phrase"
      },
      "similarity": 1000.0,
      "alternate_term_match": true
    },
    {
      "metadata": {
        "doc_id": "78",
        "name": "Improper Neutralization of Special Elements used in an OS Command ('OS Command Injection')",
        "source": "alternate_terms",
        "original_matched_text": "AlternateTerms: OS Command Injection",
        "match_reason": "phrase_in_term_whole_phrase"
      },
      "similarity": 700.0,
      "alternate_term_match": true
    },
    {
      "metadata": {
        "doc_id": "94",
        "name": "Improper Control of Generation of Code ('Code Injection')",
        "source": "sparse"
      },
      "similarity": 233.7382884582073
    },
    {
      "metadata": {
        "doc_id": "138",
        "name": "Improper Neutralization of Special Elements",
        "source": "sparse"
      },
      "similarity": 231.52336340062791
    },
    {
      "metadata": {
        "doc_id": "79",
        "name": "Improper Neutralization of Input During Web Page Generation ('Cross-site Scripting')",
        "source": "sparse"
      },
      "similarity": 230.6498008651272
    },
    {
      "metadata": {
        "doc_id": "88",
        "name": "Improper Neutralization of Argument Delimiters in a Command ('Argument Injection')",
        "source": "sparse"
      },
      "similarity": 229.1908581570235
    },
    {
      "metadata": {
        "doc_id": "95",
        "name": "Improper Neutralization of Directives in Dynamically Evaluated Code ('Eval Injection')",
        "source": "sparse"
      },
      "similarity": 227.8851200276928
    },
    {
      "metadata": {
        "doc_id": "502",
        "name": "Deserialization of Untrusted Data",
        "source": "sparse"
      },
      "similarity": 227.41156430201357
    },
    {
      "metadata": {
        "doc_id": "96",
        "name": "Improper Neutralization of Directives in Statically Saved Code ('Static Code Injection')",
        "type": "Base",
        "original_content": "The product receives input from an upstream component, but it does not neutralize or incorrectly neutralizes code syntax before inserting the input into an executable resource, such as a library, configuration file, or template.",
        "keyphrase_source": "weakness:command injection",
        "source": "dense",
        "mapping_notes": {
          "usage": "Allowed",
          "rationale": "This CWE entry is at the Base level of abstraction, which is a preferred level of abstraction for mapping to the root causes of vulnerabilities.",
          "comments": "Carefully read both the name and description to ensure that this mapping is an appropriate fit. Do not try to 'force' a mapping to a lower-level Base/Variant simply to comply with this preferred level of abstraction.",
          "reasons": [
            "Acceptable-Use"
          ]
        },
        "score_info": {
          "retrievers": [
            "dense",
            "graph"
          ],
          "retriever_count": 2,
          "normalized_scores": {
            "dense": 0.5742016846735701,
            "graph": 1.7234343941822248
          }
        }
      },
      "similarity": 0.5742016846735701
    },
    {
      "doc_id": "89",
      "text": "The product constructs all or part of an SQL command using externally-influenced input from an upstream component, but it does not neutralize or incorrectly neutralizes special elements that could modify the intended SQL command when it is sent to a downstream component. Without sufficient removal or quoting of SQL syntax in user-controllable inputs, the generated SQL query can cause those inputs to be interpreted as SQL instead of ordinary user data.",
      "score": 0.5737824526488132,
      "metadata": {
        "doc_id": "89",
        "name": "Improper Neutralization of Special Elements used in an SQL Command ('SQL Injection')",
        "type": "Base",
        "extended_description": null,
        "alternate_terms": [
          "SQL injection",
          "SQLi"
        ],
        "original_content": "The product constructs all or part of an SQL command using externally-influenced input from an upstream component, but it does not neutralize or incorrectly neutralizes special elements that could modify the intended SQL command when it is sent to a downstream component. Without sufficient removal or quoting of SQL syntax in user-controllable inputs, the generated SQL query can cause those inputs to be interpreted as SQL instead of ordinary user data.",
        "relationships": [
          {
            "source_id": "89",
            "target_id": "564",
            "label": "PARENTOF",
            "properties": {
              "ordinal": "Primary",
              "view_id": "1000"
            }
          },
          {
            "source_id": "89",
            "target_id": "456",
            "label": "CANFOLLOW",
            "properties": {
              "view_id": "1000"
            }
          },
          {
            "source_id": "89",
            "target_id": "74",
            "label": "CHILDOF",
            "properties": {
              "ordinal": "Primary",
              "view_id": "1003"
            }
          },
          {
            "source_id": "89",
            "target_id": "943",
            "label": "CHILDOF",
            "properties": {
              "ordinal": "Primary",
              "view_id": "1000"
            }
          },
          {
            "source_id": "943",
            "target_id": "89",
            "label": "PARENTOF",
            "properties": {
              "ordinal": "Primary",
              "view_id": "1000"
            }
          },
          {
            "source_id": "74",
            "target_id": "89",
            "label": "PARENTOF",
            "properties": {
              "ordinal": "Primary",
              "view_id": "1003"
            }
          },
          {
            "source_id": "564",
            "target_id": "89",
            "label": "CHILDOF",
            "properties": {
              "ordinal": "Primary",
              "view_id": "1305"
            }
          },
          {
            "source_id": "564",
            "target_id": "89",
            "label": "CHILDOF",
            "properties": {
              "ordinal": "Primary",
              "view_id": "928"
            }
          },
          {
            "source_id": "564",
            "target_id": "89",
            "label": "CHILDOF",
            "properties": {
              "ordinal": "Primary",
              "view_id": "1000"
            }
          },
          {
            "source_id": "456",
            "target_id": "89",
            "label": "CANPRECEDE",
            "properties": {
              "view_id": "1000"
            }
          }
        ],
        "source": "graph",
        "sources": [
          "vector",
          "graph"
        ],
        "vector_score": 0.5737824526488132,
        "graph_score": 3.4866,
        "score_components": {
          "relationship_chain": 0.6,
          "explicit_mention": 1.0,
          "abstraction_path": 0.9,
          "sequence_path": 0.6400000000000001
        },
        "abstraction_factor": 1.3,
        "graph_path_info": {
          "path_types": [
            "relationship_chain",
            "vulnerability_sequence_forward"
          ],
          "best_paths": {
            "relationship_chain": {
              "path": [
                [
                  "94",
                  "98",
                  "CANFOLLOW"
                ],
                [
                  "98",
                  "456",
                  "CANFOLLOW"
                ],
                [
                  "456",
                  "89",
                  "CANPRECEDE"
                ]
              ],
              "score": 0.6,
              "type": "relationship_chain",
              "source": "94"
            },
            "vulnerability_sequence_forward": {
              "path": [
                [
                  "94",
                  "98",
                  "CANFOLLOW"
                ],
                [
                  "98",
                  "456",
                  "CANFOLLOW"
                ],
                [
                  "456",
                  "89",
                  "CANPRECEDE"
                ]
              ],
              "score": 0.6400000000000001,
              "type": "vulnerability_sequence_forward",
              "source": "94"
            }
          }
        },
        "is_explicit": true,
        "abstraction_level": "base",
        "position": "after",
        "mapping_notes": {
          "usage": "Allowed",
          "rationale": "This CWE entry is at the Base level of abstraction, which is a preferred level of abstraction for mapping to the root causes of vulnerabilities.",
          "comments": "Carefully read both the name and description to ensure that this mapping is an appropriate fit. Do not try to 'force' a mapping to a lower-level Base/Variant simply to comply with this preferred level of abstraction.",
          "reasons": [
            "Acceptable-Use"
          ]
        },
        "score_info": {
          "retrievers": [
            "dense",
            "sparse",
            "graph"
          ],
          "retriever_count": 3,
          "normalized_scores": {
            "dense": 0.5540019918127375,
            "sparse": 225.01305097534686,
            "graph": 2.321472981059525
          }
        }
      },
      "similarity": 2.321472981059525
    }
  ],
  "identified_cwes": {
    "analyzer": [
      "CWE-777",
      "CWE-697",
      "CWE-187",
      "CWE-185",
      "CWE-942",
      "CWE-915",
      "CWE-98",
      "CWE-85",
      "CWE-84",
      "CWE-1289",
      "CWE-1336",
      "CWE-434",
      "CWE-427",
      "CWE-642",
      "CWE-77",
      "CWE-78",
      "CWE-96",
      "CWE-913",
      "CWE-1236",
      "CWE-79",
      "CWE-183",
      "CWE-502",
      "CWE-943",
      "CWE-345",
      "CWE-673",
      "CWE-87",
      "CWE-494",
      "CWE-138",
      "CWE-80",
      "CWE-116",
      "CWE-184",
      "CWE-917",
      "CWE-668",
      "CWE-74",
      "CWE-95",
      "CWE-94",
      "CWE-83",
      "CWE-1321",
      "CWE-625",
      "CWE-428",
      "CWE-426",
      "CWE-669",
      "CWE-88",
      "CWE-86"
    ],
    "critic_additional": []
  }
}